[
    {
        "ingame_id": "COMMON_ACCURACY_RATE_STONE_1",
        "id": "COMMON_ACCURACY_RATE_STONE_1",
        "name": "TEXT_COMMON_ACCURACY_RATE_STONE_1_TITLE",
        "description": "TEXT_COMMON_ACCURACY_RATE_STONE_1_DESC",
        "image": "ui_item_stone_1_func",
        "grade": 1,
        "rarity": "common",
        "sell_cost": 500,
        "extract_cost": 100000,
        "stats": {
            "atk_power": 0,
            "hp": 0,
            "crit_chance": 0,
            "armor": 0,
            "resistance": 0,
            "crit_dmg": 0,
            "accuracy": 0.01,
            "evasion": 0,
            "armor_pen": 0,
            "resistance_pen": 0,
            "dmg_reduction": 0,
            "lifesteal": 0,
            "crit_chance_reduction": 0
        },
        "set": null
    },
    {
        "ingame_id": "COMMON_ATK_POWER_STONE_1",
        "id": "COMMON_ATK_POWER_STONE_1",
        "name": "TEXT_COMMON_ATK_POWER_STONE_1_TITLE",
        "description": "TEXT_COMMON_ATK_POWER_STONE_1_DESC",
        "image": "ui_item_stone_1_atk",
        "grade": 1,
        "rarity": "common",
        "sell_cost": 500,
        "extract_cost": 100000,
        "stats": {
            "atk_power": 150,
            "hp": 0,
            "crit_chance": 0,
            "armor": 0,
            "resistance": 0,
            "crit_dmg": 0,
            "accuracy": 0,
            "evasion": 0,
            "armor_pen": 0,
            "resistance_pen": 0,
            "dmg_reduction": 0,
            "lifesteal": 0,
            "crit_chance_reduction": 0
        },
        "set": null
    },
    {
        "ingame_id": "COMMON_BOUILLABAISSE_STONE_1",
        "id": "COMMON_BOUILLABAISSE_STONE_1",
        "name": "TEXT_COMMON_BOUILLABAISSE_STONE_1_TITLE",
        "description": "TEXT_COMMON_BOUILLABAISSE_STONE_1_DESC",
        "image": "ui_item_stone_1_legend_19",
        "grade": 1,
        "rarity": "common",
        "sell_cost": 500,
        "extract_cost": 100000,
        "stats": {
            "atk_power": 0,
            "hp": 0,
            "crit_chance": 0,
            "armor": 0,
            "resistance": 0,
            "crit_dmg": 0,
            "accuracy": 0,
            "evasion": 0,
            "armor_pen": 150,
            "resistance_pen": 0,
            "dmg_reduction": 0,
            "lifesteal": 0,
            "crit_chance_reduction": 0
        },
        "set": null
    },
    {
        "ingame_id": "COMMON_BOUILLABAISSE_STONE_2",
        "id": "COMMON_BOUILLABAISSE_STONE_2",
        "name": "TEXT_COMMON_BOUILLABAISSE_STONE_2_TITLE",
        "description": "TEXT_COMMON_BOUILLABAISSE_STONE_2_DESC",
        "image": "ui_item_stone_1_legend_20",
        "grade": 1,
        "rarity": "common",
        "sell_cost": 500,
        "extract_cost": 100000,
        "stats": {
            "atk_power": 0,
            "hp": 0,
            "crit_chance": 0,
            "armor": 0,
            "resistance": 0,
            "crit_dmg": 0,
            "accuracy": 0,
            "evasion": 0,
            "armor_pen": 0,
            "resistance_pen": 150,
            "dmg_reduction": 0,
            "lifesteal": 0,
            "crit_chance_reduction": 0
        },
        "set": null
    },
    {
        "ingame_id": "COMMON_CRIT_DODGE_RATE_STONE_1",
        "id": "COMMON_CRIT_DODGE_RATE_STONE_1",
        "name": "TEXT_COMMON_CRIT_DODGE_RATE_STONE_1_TITLE",
        "description": "TEXT_COMMON_CRIT_DODGE_RATE_STONE_1_DESC",
        "image": "ui_item_stone_1_def",
        "grade": 1,
        "rarity": "common",
        "sell_cost": 500,
        "extract_cost": 100000,
        "stats": {
            "atk_power": 0,
            "hp": 0,
            "crit_chance": 0,
            "armor": 0,
            "resistance": 0,
            "crit_dmg": 0,
            "accuracy": 0,
            "evasion": 0,
            "armor_pen": 0,
            "resistance_pen": 0,
            "dmg_reduction": 0,
            "lifesteal": 0,
            "crit_chance_reduction": 0.01
        },
        "set": null
    },
    {
        "ingame_id": "COMMON_CRIT_RATE_STONE_1",
        "id": "COMMON_CRIT_RATE_STONE_1",
        "name": "TEXT_COMMON_CRIT_RATE_STONE_1_TITLE",
        "description": "TEXT_COMMON_CRIT_RATE_STONE_1_DESC",
        "image": "ui_item_stone_1_func",
        "grade": 1,
        "rarity": "common",
        "sell_cost": 500,
        "extract_cost": 100000,
        "stats": {
            "atk_power": 0,
            "hp": 0,
            "crit_chance": 0.01,
            "armor": 0,
            "resistance": 0,
            "crit_dmg": 0,
            "accuracy": 0,
            "evasion": 0,
            "armor_pen": 0,
            "resistance_pen": 0,
            "dmg_reduction": 0,
            "lifesteal": 0,
            "crit_chance_reduction": 0
        },
        "set": null
    },
    {
        "ingame_id": "COMMON_DEF_STONE_1",
        "id": "COMMON_DEF_STONE_1",
        "name": "TEXT_COMMON_DEF_STONE_1_TITLE",
        "description": "TEXT_COMMON_DEF_STONE_1_DESC",
        "image": "ui_item_stone_1_def",
        "grade": 1,
        "rarity": "common",
        "sell_cost": 500,
        "extract_cost": 100000,
        "stats": {
            "atk_power": 0,
            "hp": 0,
            "crit_chance": 0,
            "armor": 150,
            "resistance": 0,
            "crit_dmg": 0,
            "accuracy": 0,
            "evasion": 0,
            "armor_pen": 0,
            "resistance_pen": 0,
            "dmg_reduction": 0,
            "lifesteal": 0,
            "crit_chance_reduction": 0
        },
        "set": null
    },
    {
        "ingame_id": "COMMON_DODGE_RATE_STONE_1",
        "id": "COMMON_DODGE_RATE_STONE_1",
        "name": "TEXT_COMMON_DODGE_RATE_STONE_1_TITLE",
        "description": "TEXT_COMMON_DODGE_RATE_STONE_1_DESC",
        "image": "ui_item_stone_1_func",
        "grade": 1,
        "rarity": "common",
        "sell_cost": 500,
        "extract_cost": 100000,
        "stats": {
            "atk_power": 0,
            "hp": 0,
            "crit_chance": 0,
            "armor": 0,
            "resistance": 0,
            "crit_dmg": 0,
            "accuracy": 0,
            "evasion": 0.01,
            "armor_pen": 0,
            "resistance_pen": 0,
            "dmg_reduction": 0,
            "lifesteal": 0,
            "crit_chance_reduction": 0
        },
        "set": null
    },
    {
        "ingame_id": "COMMON_DOMPERIGNON_STONE_1",
        "id": "COMMON_DOMPERIGNON_STONE_1",
        "name": "TEXT_COMMON_DOMPERIGNON_STONE_1_TITLE",
        "description": "TEXT_COMMON_DOMPERIGNON_STONE_1_DESC",
        "image": "ui_item_stone_1_legend_16",
        "grade": 1,
        "rarity": "common",
        "sell_cost": 500,
        "extract_cost": 100000,
        "stats": {
            "atk_power": 0,
            "hp": 0,
            "crit_chance": 0,
            "armor": 150,
            "resistance": 0,
            "crit_dmg": 0,
            "accuracy": 0,
            "evasion": 0,
            "armor_pen": 0,
            "resistance_pen": 0,
            "dmg_reduction": 0,
            "lifesteal": 0,
            "crit_chance_reduction": 0
        },
        "set": null
    },
    {
        "ingame_id": "COMMON_DOMPERIGNON_STONE_2",
        "id": "COMMON_DOMPERIGNON_STONE_2",
        "name": "TEXT_COMMON_DOMPERIGNON_STONE_2_TITLE",
        "description": "TEXT_COMMON_DOMPERIGNON_STONE_2_DESC",
        "image": "ui_item_stone_1_legend_17",
        "grade": 1,
        "rarity": "common",
        "sell_cost": 500,
        "extract_cost": 100000,
        "stats": {
            "atk_power": 0,
            "hp": 0,
            "crit_chance": 0,
            "armor": 0,
            "resistance": 150,
            "crit_dmg": 0,
            "accuracy": 0,
            "evasion": 0,
            "armor_pen": 0,
            "resistance_pen": 0,
            "dmg_reduction": 0,
            "lifesteal": 0,
            "crit_chance_reduction": 0
        },
        "set": null
    },
    {
        "ingame_id": "COMMON_GOBLINCHIEF_STONE_1",
        "id": "COMMON_GOBLINCHIEF_STONE_1",
        "name": "TEXT_COMMON_GOBLINCHIEF_STONE_1_TITLE",
        "description": "TEXT_COMMON_GOBLINCHIEF_STONE_1_DESC",
        "image": "ui_item_stone_1_legend_10",
        "grade": 1,
        "rarity": "common",
        "sell_cost": 500,
        "extract_cost": 100000,
        "stats": {
            "atk_power": 0,
            "hp": 0,
            "crit_chance": 0,
            "armor": 150,
            "resistance": 0,
            "crit_dmg": 0,
            "accuracy": 0,
            "evasion": 0,
            "armor_pen": 0,
            "resistance_pen": 0,
            "dmg_reduction": 0,
            "lifesteal": 0,
            "crit_chance_reduction": 0
        },
        "set": null
    },
    {
        "ingame_id": "COMMON_GOBLINCHIEF_STONE_2",
        "id": "COMMON_GOBLINCHIEF_STONE_2",
        "name": "TEXT_COMMON_GOBLINCHIEF_STONE_2_TITLE",
        "description": "TEXT_COMMON_GOBLINCHIEF_STONE_2_DESC",
        "image": "ui_item_stone_1_legend_11",
        "grade": 1,
        "rarity": "common",
        "sell_cost": 500,
        "extract_cost": 100000,
        "stats": {
            "atk_power": 0,
            "hp": 0,
            "crit_chance": 0,
            "armor": 0,
            "resistance": 150,
            "crit_dmg": 0,
            "accuracy": 0,
            "evasion": 0,
            "armor_pen": 0,
            "resistance_pen": 0,
            "dmg_reduction": 0,
            "lifesteal": 0,
            "crit_chance_reduction": 0
        },
        "set": null
    },
    {
        "ingame_id": "COMMON_GOBLINCHIEF_STONE_3",
        "id": "COMMON_GOBLINCHIEF_STONE_3",
        "name": "TEXT_COMMON_GOBLINCHIEF_STONE_3_TITLE",
        "description": "TEXT_COMMON_GOBLINCHIEF_STONE_3_DESC",
        "image": "ui_item_stone_1_legend_12",
        "grade": 1,
        "rarity": "common",
        "sell_cost": 500,
        "extract_cost": 100000,
        "stats": {
            "atk_power": 0,
            "hp": 6000,
            "crit_chance": 0,
            "armor": 0,
            "resistance": 0,
            "crit_dmg": 0,
            "accuracy": 0,
            "evasion": 0,
            "armor_pen": 0,
            "resistance_pen": 0,
            "dmg_reduction": 0,
            "lifesteal": 0,
            "crit_chance_reduction": 0
        },
        "set": null
    },
    {
        "ingame_id": "COMMON_GOBLINMASTER_STONE_1",
        "id": "COMMON_GOBLINMASTER_STONE_1",
        "name": "TEXT_COMMON_GOBLINMASTER_STONE_1_TITLE",
        "description": "TEXT_COMMON_GOBLINMASTER_STONE_1_DESC",
        "image": "ui_item_stone_1_legend_07",
        "grade": 1,
        "rarity": "common",
        "sell_cost": 500,
        "extract_cost": 100000,
        "stats": {
            "atk_power": 0,
            "hp": 0,
            "crit_chance": 0.01,
            "armor": 0,
            "resistance": 0,
            "crit_dmg": 0,
            "accuracy": 0,
            "evasion": 0,
            "armor_pen": 0,
            "resistance_pen": 0,
            "dmg_reduction": 0,
            "lifesteal": 0,
            "crit_chance_reduction": 0
        },
        "set": null
    },
    {
        "ingame_id": "COMMON_GOBLINMASTER_STONE_2",
        "id": "COMMON_GOBLINMASTER_STONE_2",
        "name": "TEXT_COMMON_GOBLINMASTER_STONE_2_TITLE",
        "description": "TEXT_COMMON_GOBLINMASTER_STONE_2_DESC",
        "image": "ui_item_stone_1_legend_08",
        "grade": 1,
        "rarity": "common",
        "sell_cost": 500,
        "extract_cost": 100000,
        "stats": {
            "atk_power": 0,
            "hp": 0,
            "crit_chance": 0,
            "armor": 0,
            "resistance": 0,
            "crit_dmg": 0,
            "accuracy": 0,
            "evasion": 0,
            "armor_pen": 0,
            "resistance_pen": 0,
            "dmg_reduction": 0,
            "lifesteal": 0,
            "crit_chance_reduction": 0.01
        },
        "set": null
    },
    {
        "ingame_id": "COMMON_GOBLINMASTER_STONE_3",
        "id": "COMMON_GOBLINMASTER_STONE_3",
        "name": "TEXT_COMMON_GOBLINMASTER_STONE_3_TITLE",
        "description": "TEXT_COMMON_GOBLINMASTER_STONE_3_DESC",
        "image": "ui_item_stone_1_legend_09",
        "grade": 1,
        "rarity": "common",
        "sell_cost": 500,
        "extract_cost": 100000,
        "stats": {
            "atk_power": 0,
            "hp": 6000,
            "crit_chance": 0,
            "armor": 0,
            "resistance": 0,
            "crit_dmg": 0,
            "accuracy": 0,
            "evasion": 0,
            "armor_pen": 0,
            "resistance_pen": 0,
            "dmg_reduction": 0,
            "lifesteal": 0,
            "crit_chance_reduction": 0
        },
        "set": null
    },
    {
        "ingame_id": "COMMON_KINGTIGER_STONE_1",
        "id": "COMMON_KINGTIGER_STONE_1",
        "name": "TEXT_COMMON_KINGTIGER_STONE_1_TITLE",
        "description": "TEXT_COMMON_KINGTIGER_STONE_1_DESC",
        "image": "ui_item_stone_1_legend_04",
        "grade": 1,
        "rarity": "common",
        "sell_cost": 500,
        "extract_cost": 100000,
        "stats": {
            "atk_power": 0,
            "hp": 0,
            "crit_chance": 0,
            "armor": 0,
            "resistance": 0,
            "crit_dmg": 0,
            "accuracy": 0,
            "evasion": 0.01,
            "armor_pen": 0,
            "resistance_pen": 0,
            "dmg_reduction": 0,
            "lifesteal": 0,
            "crit_chance_reduction": 0
        },
        "set": null
    },
    {
        "ingame_id": "COMMON_KINGTIGER_STONE_2",
        "id": "COMMON_KINGTIGER_STONE_2",
        "name": "TEXT_COMMON_KINGTIGER_STONE_2_TITLE",
        "description": "TEXT_COMMON_KINGTIGER_STONE_2_DESC",
        "image": "ui_item_stone_1_legend_05",
        "grade": 1,
        "rarity": "common",
        "sell_cost": 500,
        "extract_cost": 100000,
        "stats": {
            "atk_power": 0,
            "hp": 0,
            "crit_chance": 0,
            "armor": 0,
            "resistance": 0,
            "crit_dmg": 0,
            "accuracy": 0.01,
            "evasion": 0,
            "armor_pen": 0,
            "resistance_pen": 0,
            "dmg_reduction": 0,
            "lifesteal": 0,
            "crit_chance_reduction": 0
        },
        "set": null
    },
    {
        "ingame_id": "COMMON_KINGTIGER_STONE_3",
        "id": "COMMON_KINGTIGER_STONE_3",
        "name": "TEXT_COMMON_KINGTIGER_STONE_3_TITLE",
        "description": "TEXT_COMMON_KINGTIGER_STONE_3_DESC",
        "image": "ui_item_stone_1_legend_06",
        "grade": 1,
        "rarity": "common",
        "sell_cost": 500,
        "extract_cost": 100000,
        "stats": {
            "atk_power": 150,
            "hp": 0,
            "crit_chance": 0,
            "armor": 0,
            "resistance": 0,
            "crit_dmg": 0,
            "accuracy": 0,
            "evasion": 0,
            "armor_pen": 0,
            "resistance_pen": 0,
            "dmg_reduction": 0,
            "lifesteal": 0,
            "crit_chance_reduction": 0
        },
        "set": null
    },
    {
        "ingame_id": "COMMON_MATAHARI_STONE_1",
        "id": "COMMON_MATAHARI_STONE_1",
        "name": "TEXT_COMMON_MATAHARI_STONE_1_TITLE",
        "description": "TEXT_COMMON_MATAHARI_STONE_1_DESC",
        "image": "ui_item_stone_1_legend_13",
        "grade": 1,
        "rarity": "common",
        "sell_cost": 500,
        "extract_cost": 100000,
        "stats": {
            "atk_power": 0,
            "hp": 0,
            "crit_chance": 0,
            "armor": 0,
            "resistance": 0,
            "crit_dmg": 0,
            "accuracy": 0.01,
            "evasion": 0,
            "armor_pen": 0,
            "resistance_pen": 0,
            "dmg_reduction": 0,
            "lifesteal": 0,
            "crit_chance_reduction": 0
        },
        "set": null
    },
    {
        "ingame_id": "COMMON_MATAHARI_STONE_2",
        "id": "COMMON_MATAHARI_STONE_2",
        "name": "TEXT_COMMON_MATAHARI_STONE_2_TITLE",
        "description": "TEXT_COMMON_MATAHARI_STONE_2_DESC",
        "image": "ui_item_stone_1_legend_14",
        "grade": 1,
        "rarity": "common",
        "sell_cost": 500,
        "extract_cost": 100000,
        "stats": {
            "atk_power": 0,
            "hp": 0,
            "crit_chance": 0,
            "armor": 0,
            "resistance": 0,
            "crit_dmg": 0,
            "accuracy": 0,
            "evasion": 0.01,
            "armor_pen": 0,
            "resistance_pen": 0,
            "dmg_reduction": 0,
            "lifesteal": 0,
            "crit_chance_reduction": 0
        },
        "set": null
    },
    {
        "ingame_id": "COMMON_MAX_HP_STONE_1",
        "id": "COMMON_MAX_HP_STONE_1",
        "name": "TEXT_COMMON_MAX_HP_STONE_1_TITLE",
        "description": "TEXT_COMMON_MAX_HP_STONE_1_DESC",
        "image": "ui_item_stone_1_def",
        "grade": 1,
        "rarity": "common",
        "sell_cost": 500,
        "extract_cost": 100000,
        "stats": {
            "atk_power": 0,
            "hp": 6000,
            "crit_chance": 0,
            "armor": 0,
            "resistance": 0,
            "crit_dmg": 0,
            "accuracy": 0,
            "evasion": 0,
            "armor_pen": 0,
            "resistance_pen": 0,
            "dmg_reduction": 0,
            "lifesteal": 0,
            "crit_chance_reduction": 0
        },
        "set": null
    },
    {
        "ingame_id": "COMMON_PENETRATE_DEF_STONE_1",
        "id": "COMMON_PENETRATE_DEF_STONE_1",
        "name": "TEXT_COMMON_PENETRATE_DEF_STONE_1_TITLE",
        "description": "TEXT_COMMON_PENETRATE_DEF_STONE_1_DESC",
        "image": "ui_item_stone_1_atk",
        "grade": 1,
        "rarity": "common",
        "sell_cost": 500,
        "extract_cost": 100000,
        "stats": {
            "atk_power": 0,
            "hp": 0,
            "crit_chance": 0,
            "armor": 0,
            "resistance": 0,
            "crit_dmg": 0,
            "accuracy": 0,
            "evasion": 0,
            "armor_pen": 150,
            "resistance_pen": 0,
            "dmg_reduction": 0,
            "lifesteal": 0,
            "crit_chance_reduction": 0
        },
        "set": null
    },
    {
        "ingame_id": "COMMON_PENETRATE_RST_STONE_1",
        "id": "COMMON_PENETRATE_RST_STONE_1",
        "name": "TEXT_COMMON_PENETRATE_RST_STONE_1_TITLE",
        "description": "TEXT_COMMON_PENETRATE_RST_STONE_1_DESC",
        "image": "ui_item_stone_1_atk",
        "grade": 1,
        "rarity": "common",
        "sell_cost": 500,
        "extract_cost": 100000,
        "stats": {
            "atk_power": 0,
            "hp": 0,
            "crit_chance": 0,
            "armor": 0,
            "resistance": 0,
            "crit_dmg": 0,
            "accuracy": 0,
            "evasion": 0,
            "armor_pen": 0,
            "resistance_pen": 150,
            "dmg_reduction": 0,
            "lifesteal": 0,
            "crit_chance_reduction": 0
        },
        "set": null
    },
    {
        "ingame_id": "COMMON_RECEIVE_DMG_RATE_STONE_1",
        "id": "COMMON_RECEIVE_DMG_RATE_STONE_1",
        "name": "TEXT_COMMON_RECEIVE_DMG_RATE_STONE_1_TITLE",
        "description": "TEXT_COMMON_RECEIVE_DMG_RATE_STONE_1_DESC",
        "image": "ui_item_stone_1_def",
        "grade": 1,
        "rarity": "common",
        "sell_cost": 500,
        "extract_cost": 100000,
        "stats": {
            "atk_power": 0,
            "hp": 0,
            "crit_chance": 0,
            "armor": 0,
            "resistance": 0,
            "crit_dmg": 0,
            "accuracy": 0,
            "evasion": 0,
            "armor_pen": 0,
            "resistance_pen": 0,
            "dmg_reduction": 0.01,
            "lifesteal": 0,
            "crit_chance_reduction": 0
        },
        "set": null
    },
    {
        "ingame_id": "COMMON_RST_STONE_1",
        "id": "COMMON_RST_STONE_1",
        "name": "TEXT_COMMON_RST_STONE_1_TITLE",
        "description": "TEXT_COMMON_RST_STONE_1_DESC",
        "image": "ui_item_stone_1_def",
        "grade": 1,
        "rarity": "common",
        "sell_cost": 500,
        "extract_cost": 100000,
        "stats": {
            "atk_power": 0,
            "hp": 0,
            "crit_chance": 0,
            "armor": 0,
            "resistance": 150,
            "crit_dmg": 0,
            "accuracy": 0,
            "evasion": 0,
            "armor_pen": 0,
            "resistance_pen": 0,
            "dmg_reduction": 0,
            "lifesteal": 0,
            "crit_chance_reduction": 0
        },
        "set": null
    },
    {
        "ingame_id": "COMMON_SET_DEFFENCE_STONE_1",
        "id": "COMMON_SET_DEFFENCE_STONE_1",
        "name": "TEXT_COMMON_SET_DEFFENCE_STONE_1_TITLE",
        "description": "TEXT_COMMON_SET_DEFFENCE_STONE_1_DESC",
        "image": "ui_item_stone_1_set_01",
        "grade": 1,
        "rarity": "common",
        "sell_cost": 500,
        "extract_cost": 500000,
        "stats": {
            "atk_power": 0,
            "hp": 6000,
            "crit_chance": 0,
            "armor": 0,
            "resistance": 0,
            "crit_dmg": 0,
            "accuracy": 0,
            "evasion": 0,
            "armor_pen": 0,
            "resistance_pen": 0,
            "dmg_reduction": 0,
            "lifesteal": 0,
            "crit_chance_reduction": 0
        },
        "set": {
            "name": "TEXT_COMMON_SET_EP1_DEFENCE_1_NAME",
            "effect": "TEXT_COMMON_SET_EP1_DEFENCE_1_DESC",
            "pair": "COMMON_GOBLINCHIEF_STONE_1"
        }
    },
    {
        "ingame_id": "COMMON_SET_DEFFENCE_STONE_2",
        "id": "COMMON_SET_DEFFENCE_STONE_2",
        "name": "TEXT_COMMON_SET_DEFFENCE_STONE_2_TITLE",
        "description": "TEXT_COMMON_SET_DEFFENCE_STONE_2_DESC",
        "image": "ui_item_stone_1_set_02",
        "grade": 1,
        "rarity": "common",
        "sell_cost": 500,
        "extract_cost": 500000,
        "stats": {
            "atk_power": 0,
            "hp": 0,
            "crit_chance": 0,
            "armor": 0,
            "resistance": 0,
            "crit_dmg": 0,
            "accuracy": 0,
            "evasion": 0,
            "armor_pen": 0,
            "resistance_pen": 0,
            "dmg_reduction": 0.01,
            "lifesteal": 0,
            "crit_chance_reduction": 0
        },
        "set": {
            "name": "TEXT_COMMON_SET_EP1_DEFENCE_2_NAME",
            "effect": "TEXT_COMMON_SET_EP1_DEFENCE_2_DESC",
            "pair": "COMMON_GOBLINCHIEF_STONE_2"
        }
    },
    {
        "ingame_id": "COMMON_SET_HEAL_STONE_1",
        "id": "COMMON_SET_HEAL_STONE_1",
        "name": "TEXT_COMMON_SET_HEAL_STONE_1_TITLE",
        "description": "TEXT_COMMON_SET_HEAL_STONE_1_DESC",
        "image": "ui_item_stone_1_set_07",
        "grade": 1,
        "rarity": "common",
        "sell_cost": 500,
        "extract_cost": 500000,
        "stats": {
            "atk_power": 150,
            "hp": 0,
            "crit_chance": 0,
            "armor": 0,
            "resistance": 0,
            "crit_dmg": 0,
            "accuracy": 0,
            "evasion": 0,
            "armor_pen": 0,
            "resistance_pen": 0,
            "dmg_reduction": 0,
            "lifesteal": 0,
            "crit_chance_reduction": 0
        },
        "set": {
            "name": "TEXT_COMMON_SET_EP1_HEAL_1_NAME",
            "effect": "TEXT_COMMON_SET_EP1_HEAL_1_DESC",
            "pair": "COMMON_KINGTIGER_STONE_3"
        }
    },
    {
        "ingame_id": "COMMON_SET_HEAL_STONE_2",
        "id": "COMMON_SET_HEAL_STONE_2",
        "name": "TEXT_COMMON_SET_HEAL_STONE_2_TITLE",
        "description": "TEXT_COMMON_SET_HEAL_STONE_2_DESC",
        "image": "ui_item_stone_1_set_08",
        "grade": 1,
        "rarity": "common",
        "sell_cost": 500,
        "extract_cost": 500000,
        "stats": {
            "atk_power": 0,
            "hp": 6000,
            "crit_chance": 0,
            "armor": 0,
            "resistance": 0,
            "crit_dmg": 0,
            "accuracy": 0,
            "evasion": 0,
            "armor_pen": 0,
            "resistance_pen": 0,
            "dmg_reduction": 0,
            "lifesteal": 0,
            "crit_chance_reduction": 0
        },
        "set": {
            "name": "TEXT_COMMON_SET_EP1_HEAL_2_NAME",
            "effect": "TEXT_COMMON_SET_EP1_HEAL_2_DESC",
            "pair": "COMMON_GOBLINMASTER_STONE_3"
        }
    },
    {
        "ingame_id": "COMMON_SET_MAGIC_STONE_1",
        "id": "COMMON_SET_MAGIC_STONE_1",
        "name": "TEXT_COMMON_SET_MAGIC_STONE_1_TITLE",
        "description": "TEXT_COMMON_SET_MAGIC_STONE_1_DESC",
        "image": "ui_item_stone_1_set_05",
        "grade": 1,
        "rarity": "common",
        "sell_cost": 500,
        "extract_cost": 500000,
        "stats": {
            "atk_power": 150,
            "hp": 0,
            "crit_chance": 0,
            "armor": 0,
            "resistance": 0,
            "crit_dmg": 0,
            "accuracy": 0,
            "evasion": 0,
            "armor_pen": 0,
            "resistance_pen": 0,
            "dmg_reduction": 0,
            "lifesteal": 0,
            "crit_chance_reduction": 0
        },
        "set": {
            "name": "TEXT_COMMON_SET_EP1_MAGIC_1_NAME",
            "effect": "TEXT_COMMON_SET_EP1_MAGIC_1_DESC",
            "pair": "COMMON_BOUILLABAISSE_STONE_2"
        }
    },
    {
        "ingame_id": "COMMON_SET_MAGIC_STONE_2",
        "id": "COMMON_SET_MAGIC_STONE_2",
        "name": "TEXT_COMMON_SET_MAGIC_STONE_2_TITLE",
        "description": "TEXT_COMMON_SET_MAGIC_STONE_2_DESC",
        "image": "ui_item_stone_1_set_06",
        "grade": 1,
        "rarity": "common",
        "sell_cost": 500,
        "extract_cost": 500000,
        "stats": {
            "atk_power": 0,
            "hp": 0,
            "crit_chance": 0,
            "armor": 0,
            "resistance": 0,
            "crit_dmg": 0,
            "accuracy": 0,
            "evasion": 0,
            "armor_pen": 0,
            "resistance_pen": 150,
            "dmg_reduction": 0,
            "lifesteal": 0,
            "crit_chance_reduction": 0
        },
        "set": {
            "name": "TEXT_COMMON_SET_EP1_MAGIC_2_NAME",
            "effect": "TEXT_COMMON_SET_EP1_MAGIC_2_DESC",
            "pair": "COMMON_WINDWALKER_STONE_2"
        }
    },
    {
        "ingame_id": "COMMON_SET_PHYSIC_STONE_1",
        "id": "COMMON_SET_PHYSIC_STONE_1",
        "name": "TEXT_COMMON_SET_PHYSIC_STONE_1_TITLE",
        "description": "TEXT_COMMON_SET_PHYSIC_STONE_1_DESC",
        "image": "ui_item_stone_1_set_03",
        "grade": 1,
        "rarity": "common",
        "sell_cost": 500,
        "extract_cost": 500000,
        "stats": {
            "atk_power": 150,
            "hp": 0,
            "crit_chance": 0,
            "armor": 0,
            "resistance": 0,
            "crit_dmg": 0,
            "accuracy": 0,
            "evasion": 0,
            "armor_pen": 0,
            "resistance_pen": 0,
            "dmg_reduction": 0,
            "lifesteal": 0,
            "crit_chance_reduction": 0
        },
        "set": {
            "name": "TEXT_COMMON_SET_EP1_PHYSIC_1_NAME",
            "effect": "TEXT_COMMON_SET_EP1_PHYSIC_1_DESC",
            "pair": "COMMON_BOUILLABAISSE_STONE_1"
        }
    },
    {
        "ingame_id": "COMMON_SET_PHYSIC_STONE_2",
        "id": "COMMON_SET_PHYSIC_STONE_2",
        "name": "TEXT_COMMON_SET_PHYSIC_STONE_2_TITLE",
        "description": "TEXT_COMMON_SET_PHYSIC_STONE_2_DESC",
        "image": "ui_item_stone_1_set_04",
        "grade": 1,
        "rarity": "common",
        "sell_cost": 500,
        "extract_cost": 500000,
        "stats": {
            "atk_power": 0,
            "hp": 0,
            "crit_chance": 0,
            "armor": 0,
            "resistance": 0,
            "crit_dmg": 0,
            "accuracy": 0,
            "evasion": 0,
            "armor_pen": 150,
            "resistance_pen": 0,
            "dmg_reduction": 0,
            "lifesteal": 0,
            "crit_chance_reduction": 0
        },
        "set": {
            "name": "TEXT_COMMON_SET_EP1_PHYSIC_2_NAME",
            "effect": "TEXT_COMMON_SET_EP1_PHYSIC_2_DESC",
            "pair": "COMMON_WINDWALKER_STONE_3"
        }
    },
    {
        "ingame_id": "COMMON_WINDWALKER_STONE_1",
        "id": "COMMON_WINDWALKER_STONE_1",
        "name": "TEXT_COMMON_WINDWALKER_STONE_1_TITLE",
        "description": "TEXT_COMMON_WINDWALKER_STONE_1_DESC",
        "image": "ui_item_stone_1_legend_01",
        "grade": 1,
        "rarity": "common",
        "sell_cost": 500,
        "extract_cost": 100000,
        "stats": {
            "atk_power": 0,
            "hp": 0,
            "crit_chance": 0,
            "armor": 0,
            "resistance": 0,
            "crit_dmg": 0,
            "accuracy": 0,
            "evasion": 0,
            "armor_pen": 0,
            "resistance_pen": 0,
            "dmg_reduction": 0.01,
            "lifesteal": 0,
            "crit_chance_reduction": 0
        },
        "set": null
    },
    {
        "ingame_id": "COMMON_WINDWALKER_STONE_2",
        "id": "COMMON_WINDWALKER_STONE_2",
        "name": "TEXT_COMMON_WINDWALKER_STONE_2_TITLE",
        "description": "TEXT_COMMON_WINDWALKER_STONE_2_DESC",
        "image": "ui_item_stone_1_legend_02",
        "grade": 1,
        "rarity": "common",
        "sell_cost": 500,
        "extract_cost": 100000,
        "stats": {
            "atk_power": 0,
            "hp": 0,
            "crit_chance": 0,
            "armor": 0,
            "resistance": 0,
            "crit_dmg": 0,
            "accuracy": 0,
            "evasion": 0,
            "armor_pen": 0,
            "resistance_pen": 150,
            "dmg_reduction": 0,
            "lifesteal": 0,
            "crit_chance_reduction": 0
        },
        "set": null
    },
    {
        "ingame_id": "COMMON_WINDWALKER_STONE_3",
        "id": "COMMON_WINDWALKER_STONE_3",
        "name": "TEXT_COMMON_WINDWALKER_STONE_3_TITLE",
        "description": "TEXT_COMMON_WINDWALKER_STONE_3_DESC",
        "image": "ui_item_stone_1_legend_03",
        "grade": 1,
        "rarity": "common",
        "sell_cost": 500,
        "extract_cost": 100000,
        "stats": {
            "atk_power": 0,
            "hp": 0,
            "crit_chance": 0,
            "armor": 0,
            "resistance": 0,
            "crit_dmg": 0,
            "accuracy": 0,
            "evasion": 0,
            "armor_pen": 150,
            "resistance_pen": 0,
            "dmg_reduction": 0,
            "lifesteal": 0,
            "crit_chance_reduction": 0
        },
        "set": null
    },
    {
        "ingame_id": "EPIC_3G_STONE_1",
        "id": "EPIC_3G_STONE_1",
        "name": "TEXT_EPIC_3G_STONE_1_TITLE",
        "description": "TEXT_EPIC_3G_STONE_1_DESC",
        "image": "ui_item_stone_1_legend_36",
        "grade": 1,
        "rarity": "epic",
        "sell_cost": 2000,
        "extract_cost": 500000,
        "stats": {
            "atk_power": 0,
            "hp": 0,
            "crit_chance": 0,
            "armor": 0,
            "resistance": 0,
            "crit_dmg": 0,
            "accuracy": 0,
            "evasion": 0,
            "armor_pen": 0,
            "resistance_pen": 500,
            "dmg_reduction": 0,
            "lifesteal": 0,
            "crit_chance_reduction": 0
        },
        "set": null
    },
    {
        "ingame_id": "EPIC_ACCURACY_RATE_STONE_1",
        "id": "EPIC_ACCURACY_RATE_STONE_1",
        "name": "TEXT_EPIC_ACCURACY_RATE_STONE_1_TITLE",
        "description": "TEXT_EPIC_ACCURACY_RATE_STONE_1_DESC",
        "image": "ui_item_stone_1_func",
        "grade": 1,
        "rarity": "epic",
        "sell_cost": 2000,
        "extract_cost": 500000,
        "stats": {
            "atk_power": 0,
            "hp": 0,
            "crit_chance": 0,
            "armor": 0,
            "resistance": 0,
            "crit_dmg": 0,
            "accuracy": 0.05,
            "evasion": 0,
            "armor_pen": 0,
            "resistance_pen": 0,
            "dmg_reduction": 0,
            "lifesteal": 0,
            "crit_chance_reduction": 0
        },
        "set": null
    },
    {
        "ingame_id": "EPIC_ANCIENREGIME_STONE_1",
        "id": "EPIC_ANCIENREGIME_STONE_1",
        "name": "TEXT_EPIC_ANCIENREGIME_STONE_1_TITLE",
        "description": "TEXT_EPIC_ANCIENREGIME_STONE_1_DESC",
        "image": "ui_item_stone_1_legend_22",
        "grade": 1,
        "rarity": "epic",
        "sell_cost": 2000,
        "extract_cost": 500000,
        "stats": {
            "atk_power": 0,
            "hp": 0,
            "crit_chance": 0,
            "armor": 0,
            "resistance": 0,
            "crit_dmg": 0,
            "accuracy": 0.05,
            "evasion": 0.05,
            "armor_pen": 0,
            "resistance_pen": 0,
            "dmg_reduction": 0,
            "lifesteal": 0,
            "crit_chance_reduction": 0
        },
        "set": null
    },
    {
        "ingame_id": "EPIC_ANCIENREGIME_STONE_2",
        "id": "EPIC_ANCIENREGIME_STONE_2",
        "name": "TEXT_EPIC_ANCIENREGIME_STONE_2_TITLE",
        "description": "TEXT_EPIC_ANCIENREGIME_STONE_2_DESC",
        "image": "ui_item_stone_1_legend_23",
        "grade": 1,
        "rarity": "epic",
        "sell_cost": 2000,
        "extract_cost": 500000,
        "stats": {
            "atk_power": 0,
            "hp": 0,
            "crit_chance": 0,
            "armor": 0,
            "resistance": 500,
            "crit_dmg": 0,
            "accuracy": 0,
            "evasion": 0.05,
            "armor_pen": 0,
            "resistance_pen": 0,
            "dmg_reduction": 0,
            "lifesteal": 0,
            "crit_chance_reduction": 0
        },
        "set": null
    },
    {
        "ingame_id": "EPIC_ANCIENREGIME_STONE_3",
        "id": "EPIC_ANCIENREGIME_STONE_3",
        "name": "TEXT_EPIC_ANCIENREGIME_STONE_3_TITLE",
        "description": "TEXT_EPIC_ANCIENREGIME_STONE_3_DESC",
        "image": "ui_item_stone_1_legend_24",
        "grade": 1,
        "rarity": "epic",
        "sell_cost": 2000,
        "extract_cost": 500000,
        "stats": {
            "atk_power": 0,
            "hp": 0,
            "crit_chance": 0,
            "armor": 500,
            "resistance": 0,
            "crit_dmg": 0,
            "accuracy": 0,
            "evasion": 0.05,
            "armor_pen": 0,
            "resistance_pen": 0,
            "dmg_reduction": 0,
            "lifesteal": 0,
            "crit_chance_reduction": 0
        },
        "set": null
    },
    {
        "ingame_id": "EPIC_ATK_POWER_STONE_1",
        "id": "EPIC_ATK_POWER_STONE_1",
        "name": "TEXT_EPIC_ATK_POWER_STONE_1_TITLE",
        "description": "TEXT_EPIC_ATK_POWER_STONE_1_DESC",
        "image": "ui_item_stone_1_atk",
        "grade": 1,
        "rarity": "epic",
        "sell_cost": 2000,
        "extract_cost": 500000,
        "stats": {
            "atk_power": 500,
            "hp": 0,
            "crit_chance": 0,
            "armor": 0,
            "resistance": 0,
            "crit_dmg": 0,
            "accuracy": 0,
            "evasion": 0,
            "armor_pen": 0,
            "resistance_pen": 0,
            "dmg_reduction": 0,
            "lifesteal": 0,
            "crit_chance_reduction": 0
        },
        "set": null
    },
    {
        "ingame_id": "EPIC_AVENIR_STONE_1",
        "id": "EPIC_AVENIR_STONE_1",
        "name": "TEXT_EPIC_AVENIR_STONE_1_TITLE",
        "description": "TEXT_EPIC_AVENIR_STONE_1_DESC",
        "image": "ui_item_stone_1_legend_52",
        "grade": 1,
        "rarity": "epic",
        "sell_cost": 2000,
        "extract_cost": 500000,
        "stats": {
            "atk_power": 500,
            "hp": 0,
            "crit_chance": 0,
            "armor": 0,
            "resistance": 0,
            "crit_dmg": 0,
            "accuracy": 0,
            "evasion": 0,
            "armor_pen": 0,
            "resistance_pen": 0,
            "dmg_reduction": 0,
            "lifesteal": 0,
            "crit_chance_reduction": 0.03
        },
        "set": null
    },
    {
        "ingame_id": "EPIC_AVENIR_STONE_2",
        "id": "EPIC_AVENIR_STONE_2",
        "name": "TEXT_EPIC_AVENIR_STONE_2_TITLE",
        "description": "TEXT_EPIC_AVENIR_STONE_2_DESC",
        "image": "ui_item_stone_1_legend_53",
        "grade": 1,
        "rarity": "epic",
        "sell_cost": 2000,
        "extract_cost": 500000,
        "stats": {
            "atk_power": 500,
            "hp": 0,
            "crit_chance": 0,
            "armor": 0,
            "resistance": 0,
            "crit_dmg": 0,
            "accuracy": 0,
            "evasion": 0,
            "armor_pen": 0,
            "resistance_pen": 0,
            "dmg_reduction": 0.03,
            "lifesteal": 0,
            "crit_chance_reduction": 0
        },
        "set": null
    },
    {
        "ingame_id": "EPIC_AVENIR_STONE_3",
        "id": "EPIC_AVENIR_STONE_3",
        "name": "TEXT_EPIC_AVENIR_STONE_3_TITLE",
        "description": "TEXT_EPIC_AVENIR_STONE_3_DESC",
        "image": "ui_item_stone_1_legend_54",
        "grade": 1,
        "rarity": "epic",
        "sell_cost": 2000,
        "extract_cost": 500000,
        "stats": {
            "atk_power": 500,
            "hp": 20000,
            "crit_chance": 0,
            "armor": 0,
            "resistance": 0,
            "crit_dmg": 0,
            "accuracy": 0,
            "evasion": 0,
            "armor_pen": 0,
            "resistance_pen": 0,
            "dmg_reduction": 0,
            "lifesteal": 0,
            "crit_chance_reduction": 0
        },
        "set": null
    },
    {
        "ingame_id": "EPIC_AZATHOTH_STONE_1",
        "id": "EPIC_AZATHOTH_STONE_1",
        "name": "TEXT_EPIC_AZATHOTH_STONE_1_TITLE",
        "description": "TEXT_EPIC_AZATHOTH_STONE_1_DESC",
        "image": "ui_item_stone_1_legend_37",
        "grade": 1,
        "rarity": "epic",
        "sell_cost": 2000,
        "extract_cost": 500000,
        "stats": {
            "atk_power": 0,
            "hp": 0,
            "crit_chance": 0.03,
            "armor": 0,
            "resistance": 0,
            "crit_dmg": 0,
            "accuracy": 0,
            "evasion": 0,
            "armor_pen": 0,
            "resistance_pen": 0,
            "dmg_reduction": 0,
            "lifesteal": 0,
            "crit_chance_reduction": 0.03
        },
        "set": null
    },
    {
        "ingame_id": "EPIC_AZATHOTH_STONE_2",
        "id": "EPIC_AZATHOTH_STONE_2",
        "name": "TEXT_EPIC_AZATHOTH_STONE_2_TITLE",
        "description": "TEXT_EPIC_AZATHOTH_STONE_2_DESC",
        "image": "ui_item_stone_1_legend_38",
        "grade": 1,
        "rarity": "epic",
        "sell_cost": 2000,
        "extract_cost": 500000,
        "stats": {
            "atk_power": 0,
            "hp": 0,
            "crit_chance": 0,
            "armor": 0,
            "resistance": 0,
            "crit_dmg": 0,
            "accuracy": 0.05,
            "evasion": 0,
            "armor_pen": 500,
            "resistance_pen": 0,
            "dmg_reduction": 0,
            "lifesteal": 0,
            "crit_chance_reduction": 0
        },
        "set": null
    },
    {
        "ingame_id": "EPIC_AZATHOTH_STONE_3",
        "id": "EPIC_AZATHOTH_STONE_3",
        "name": "TEXT_EPIC_AZATHOTH_STONE_3_TITLE",
        "description": "TEXT_EPIC_AZATHOTH_STONE_3_DESC",
        "image": "ui_item_stone_1_legend_39",
        "grade": 1,
        "rarity": "epic",
        "sell_cost": 2000,
        "extract_cost": 500000,
        "stats": {
            "atk_power": 0,
            "hp": 0,
            "crit_chance": 0,
            "armor": 0,
            "resistance": 0,
            "crit_dmg": 0,
            "accuracy": 0.05,
            "evasion": 0,
            "armor_pen": 0,
            "resistance_pen": 500,
            "dmg_reduction": 0,
            "lifesteal": 0,
            "crit_chance_reduction": 0
        },
        "set": null
    },
    {
        "ingame_id": "EPIC_CRIT_DODGE_RATE_STONE_1",
        "id": "EPIC_CRIT_DODGE_RATE_STONE_1",
        "name": "TEXT_EPIC_CRIT_DODGE_RATE_STONE_1_TITLE",
        "description": "TEXT_EPIC_CRIT_DODGE_RATE_STONE_1_DESC",
        "image": "ui_item_stone_1_def",
        "grade": 1,
        "rarity": "epic",
        "sell_cost": 2000,
        "extract_cost": 500000,
        "stats": {
            "atk_power": 0,
            "hp": 0,
            "crit_chance": 0,
            "armor": 0,
            "resistance": 0,
            "crit_dmg": 0,
            "accuracy": 0,
            "evasion": 0,
            "armor_pen": 0,
            "resistance_pen": 0,
            "dmg_reduction": 0,
            "lifesteal": 0,
            "crit_chance_reduction": 0.03
        },
        "set": null
    },
    {
        "ingame_id": "EPIC_CRIT_RATE_STONE_1",
        "id": "EPIC_CRIT_RATE_STONE_1",
        "name": "TEXT_EPIC_CRIT_RATE_STONE_1_TITLE",
        "description": "TEXT_EPIC_CRIT_RATE_STONE_1_DESC",
        "image": "ui_item_stone_1_func",
        "grade": 1,
        "rarity": "epic",
        "sell_cost": 2000,
        "extract_cost": 500000,
        "stats": {
            "atk_power": 0,
            "hp": 0,
            "crit_chance": 0.03,
            "armor": 0,
            "resistance": 0,
            "crit_dmg": 0,
            "accuracy": 0,
            "evasion": 0,
            "armor_pen": 0,
            "resistance_pen": 0,
            "dmg_reduction": 0,
            "lifesteal": 0,
            "crit_chance_reduction": 0
        },
        "set": null
    },
    {
        "ingame_id": "EPIC_DEF_STONE_1",
        "id": "EPIC_DEF_STONE_1",
        "name": "TEXT_EPIC_DEF_STONE_1_TITLE",
        "description": "TEXT_EPIC_DEF_STONE_1_DESC",
        "image": "ui_item_stone_1_def",
        "grade": 1,
        "rarity": "epic",
        "sell_cost": 2000,
        "extract_cost": 500000,
        "stats": {
            "atk_power": 0,
            "hp": 0,
            "crit_chance": 0,
            "armor": 500,
            "resistance": 0,
            "crit_dmg": 0,
            "accuracy": 0,
            "evasion": 0,
            "armor_pen": 0,
            "resistance_pen": 0,
            "dmg_reduction": 0,
            "lifesteal": 0,
            "crit_chance_reduction": 0
        },
        "set": null
    },
    {
        "ingame_id": "EPIC_DODGE_RATE_STONE_1",
        "id": "EPIC_DODGE_RATE_STONE_1",
        "name": "TEXT_EPIC_DODGE_RATE_STONE_1_TITLE",
        "description": "TEXT_EPIC_DODGE_RATE_STONE_1_DESC",
        "image": "ui_item_stone_1_func",
        "grade": 1,
        "rarity": "epic",
        "sell_cost": 2000,
        "extract_cost": 500000,
        "stats": {
            "atk_power": 0,
            "hp": 0,
            "crit_chance": 0,
            "armor": 0,
            "resistance": 0,
            "crit_dmg": 0,
            "accuracy": 0,
            "evasion": 0.05,
            "armor_pen": 0,
            "resistance_pen": 0,
            "dmg_reduction": 0,
            "lifesteal": 0,
            "crit_chance_reduction": 0
        },
        "set": null
    },
    {
        "ingame_id": "EPIC_GG_STONE_1",
        "id": "EPIC_GG_STONE_1",
        "name": "TEXT_EPIC_GG_STONE_1_TITLE",
        "description": "TEXT_EPIC_GG_STONE_1_DESC",
        "image": "ui_item_stone_1_legend_30",
        "grade": 1,
        "rarity": "epic",
        "sell_cost": 2000,
        "extract_cost": 500000,
        "stats": {
            "atk_power": 0,
            "hp": 0,
            "crit_chance": 0,
            "armor": 500,
            "resistance": 0,
            "crit_dmg": 0,
            "accuracy": 0,
            "evasion": 0,
            "armor_pen": 0,
            "resistance_pen": 0,
            "dmg_reduction": 0,
            "lifesteal": 0,
            "crit_chance_reduction": 0
        },
        "set": null
    },
    {
        "ingame_id": "EPIC_LEESIN_STONE_1",
        "id": "EPIC_LEESIN_STONE_1",
        "name": "TEXT_EPIC_LEESIN_STONE_1_TITLE",
        "description": "TEXT_EPIC_LEESIN_STONE_1_DESC",
        "image": "ui_item_stone_1_legend_33",
        "grade": 1,
        "rarity": "epic",
        "sell_cost": 2000,
        "extract_cost": 500000,
        "stats": {
            "atk_power": 0,
            "hp": 0,
            "crit_chance": 0,
            "armor": 0,
            "resistance": 500,
            "crit_dmg": 0,
            "accuracy": 0,
            "evasion": 0,
            "armor_pen": 0,
            "resistance_pen": 0,
            "dmg_reduction": 0,
            "lifesteal": 0,
            "crit_chance_reduction": 0
        },
        "set": null
    },
    {
        "ingame_id": "EPIC_MAX_HP_STONE_1",
        "id": "EPIC_MAX_HP_STONE_1",
        "name": "TEXT_EPIC_MAX_HP_STONE_1_TITLE",
        "description": "TEXT_EPIC_MAX_HP_STONE_1_DESC",
        "image": "ui_item_stone_1_def",
        "grade": 1,
        "rarity": "epic",
        "sell_cost": 2000,
        "extract_cost": 500000,
        "stats": {
            "atk_power": 0,
            "hp": 20000,
            "crit_chance": 0,
            "armor": 0,
            "resistance": 0,
            "crit_dmg": 0,
            "accuracy": 0,
            "evasion": 0,
            "armor_pen": 0,
            "resistance_pen": 0,
            "dmg_reduction": 0,
            "lifesteal": 0,
            "crit_chance_reduction": 0
        },
        "set": null
    },
    {
        "ingame_id": "EPIC_PENETRATE_DEF_STONE_1",
        "id": "EPIC_PENETRATE_DEF_STONE_1",
        "name": "TEXT_EPIC_PENETRATE_DEF_STONE_1_TITLE",
        "description": "TEXT_EPIC_PENETRATE_DEF_STONE_1_DESC",
        "image": "ui_item_stone_1_atk",
        "grade": 1,
        "rarity": "epic",
        "sell_cost": 2000,
        "extract_cost": 500000,
        "stats": {
            "atk_power": 0,
            "hp": 0,
            "crit_chance": 0,
            "armor": 0,
            "resistance": 0,
            "crit_dmg": 0,
            "accuracy": 0,
            "evasion": 0,
            "armor_pen": 500,
            "resistance_pen": 0,
            "dmg_reduction": 0,
            "lifesteal": 0,
            "crit_chance_reduction": 0
        },
        "set": null
    },
    {
        "ingame_id": "EPIC_PENETRATE_RST_STONE_1",
        "id": "EPIC_PENETRATE_RST_STONE_1",
        "name": "TEXT_EPIC_PENETRATE_RST_STONE_1_TITLE",
        "description": "TEXT_EPIC_PENETRATE_RST_STONE_1_DESC",
        "image": "ui_item_stone_1_atk",
        "grade": 1,
        "rarity": "epic",
        "sell_cost": 2000,
        "extract_cost": 500000,
        "stats": {
            "atk_power": 0,
            "hp": 0,
            "crit_chance": 0,
            "armor": 0,
            "resistance": 0,
            "crit_dmg": 0,
            "accuracy": 0,
            "evasion": 0,
            "armor_pen": 0,
            "resistance_pen": 500,
            "dmg_reduction": 0,
            "lifesteal": 0,
            "crit_chance_reduction": 0
        },
        "set": null
    },
    {
        "ingame_id": "EPIC_REBOUILLABAISSE_STONE_1",
        "id": "EPIC_REBOUILLABAISSE_STONE_1",
        "name": "TEXT_EPIC_REBOUILLABAISSE_STONE_1_TITLE",
        "description": "TEXT_EPIC_REBOUILLABAISSE_STONE_1_DESC",
        "image": "ui_item_stone_1_legend_49",
        "grade": 1,
        "rarity": "epic",
        "sell_cost": 2000,
        "extract_cost": 500000,
        "stats": {
            "atk_power": 0,
            "hp": 0,
            "crit_chance": 0,
            "armor": 0,
            "resistance": 0,
            "crit_dmg": 0,
            "accuracy": 0.05,
            "evasion": 0,
            "armor_pen": 0,
            "resistance_pen": 0,
            "dmg_reduction": 0,
            "lifesteal": 0,
            "crit_chance_reduction": 0
        },
        "set": null
    },
    {
        "ingame_id": "EPIC_REBOUILLABAISSE_STONE_2",
        "id": "EPIC_REBOUILLABAISSE_STONE_2",
        "name": "TEXT_EPIC_REBOUILLABAISSE_STONE_2_TITLE",
        "description": "TEXT_EPIC_REBOUILLABAISSE_STONE_2_DESC",
        "image": "ui_item_stone_1_legend_50",
        "grade": 1,
        "rarity": "epic",
        "sell_cost": 2000,
        "extract_cost": 500000,
        "stats": {
            "atk_power": 0,
            "hp": 0,
            "crit_chance": 0,
            "armor": 0,
            "resistance": 0,
            "crit_dmg": 0,
            "accuracy": 0,
            "evasion": 0,
            "armor_pen": 0,
            "resistance_pen": 500,
            "dmg_reduction": 0,
            "lifesteal": 0,
            "crit_chance_reduction": 0
        },
        "set": null
    },
    {
        "ingame_id": "EPIC_REBOUILLABAISSE_STONE_3",
        "id": "EPIC_REBOUILLABAISSE_STONE_3",
        "name": "TEXT_EPIC_REBOUILLABAISSE_STONE_3_TITLE",
        "description": "TEXT_EPIC_REBOUILLABAISSE_STONE_3_DESC",
        "image": "ui_item_stone_1_legend_51",
        "grade": 1,
        "rarity": "epic",
        "sell_cost": 2000,
        "extract_cost": 500000,
        "stats": {
            "atk_power": 0,
            "hp": 0,
            "crit_chance": 0,
            "armor": 0,
            "resistance": 0,
            "crit_dmg": 0,
            "accuracy": 0,
            "evasion": 0,
            "armor_pen": 500,
            "resistance_pen": 0,
            "dmg_reduction": 0,
            "lifesteal": 0,
            "crit_chance_reduction": 0
        },
        "set": null
    },
    {
        "ingame_id": "EPIC_RECEIVE_DMG_RATE_STONE_1",
        "id": "EPIC_RECEIVE_DMG_RATE_STONE_1",
        "name": "TEXT_EPIC_RECEIVE_DMG_RATE_STONE_1_TITLE",
        "description": "TEXT_EPIC_RECEIVE_DMG_RATE_STONE_1_DESC",
        "image": "ui_item_stone_1_def",
        "grade": 1,
        "rarity": "epic",
        "sell_cost": 2000,
        "extract_cost": 500000,
        "stats": {
            "atk_power": 0,
            "hp": 0,
            "crit_chance": 0,
            "armor": 0,
            "resistance": 0,
            "crit_dmg": 0,
            "accuracy": 0,
            "evasion": 0,
            "armor_pen": 0,
            "resistance_pen": 0,
            "dmg_reduction": 0.03,
            "lifesteal": 0,
            "crit_chance_reduction": 0
        },
        "set": null
    },
    {
        "ingame_id": "EPIC_REDOMPERIGNON_STONE_1",
        "id": "EPIC_REDOMPERIGNON_STONE_1",
        "name": "TEXT_EPIC_REDOMPERIGNON_STONE_1_TITLE",
        "description": "TEXT_EPIC_REDOMPERIGNON_STONE_1_DESC",
        "image": "ui_item_stone_1_legend_46",
        "grade": 1,
        "rarity": "epic",
        "sell_cost": 2000,
        "extract_cost": 500000,
        "stats": {
            "atk_power": 0,
            "hp": 0,
            "crit_chance": 0,
            "armor": 0,
            "resistance": 0,
            "crit_dmg": 0,
            "accuracy": 0,
            "evasion": 0,
            "armor_pen": 0,
            "resistance_pen": 0,
            "dmg_reduction": 0.03,
            "lifesteal": 0,
            "crit_chance_reduction": 0
        },
        "set": null
    },
    {
        "ingame_id": "EPIC_REDOMPERIGNON_STONE_2",
        "id": "EPIC_REDOMPERIGNON_STONE_2",
        "name": "TEXT_EPIC_REDOMPERIGNON_STONE_2_TITLE",
        "description": "TEXT_EPIC_REDOMPERIGNON_STONE_2_DESC",
        "image": "ui_item_stone_1_legend_47",
        "grade": 1,
        "rarity": "epic",
        "sell_cost": 2000,
        "extract_cost": 500000,
        "stats": {
            "atk_power": 0,
            "hp": 0,
            "crit_chance": 0,
            "armor": 0,
            "resistance": 0,
            "crit_dmg": 0,
            "accuracy": 0,
            "evasion": 0,
            "armor_pen": 0,
            "resistance_pen": 0,
            "dmg_reduction": 0,
            "lifesteal": 0,
            "crit_chance_reduction": 0.03
        },
        "set": null
    },
    {
        "ingame_id": "EPIC_REDOMPERIGNON_STONE_3",
        "id": "EPIC_REDOMPERIGNON_STONE_3",
        "name": "TEXT_EPIC_REDOMPERIGNON_STONE_3_TITLE",
        "description": "TEXT_EPIC_REDOMPERIGNON_STONE_3_DESC",
        "image": "ui_item_stone_1_legend_48",
        "grade": 1,
        "rarity": "epic",
        "sell_cost": 2000,
        "extract_cost": 500000,
        "stats": {
            "atk_power": 0,
            "hp": 0,
            "crit_chance": 0,
            "armor": 500,
            "resistance": 0,
            "crit_dmg": 0,
            "accuracy": 0,
            "evasion": 0,
            "armor_pen": 0,
            "resistance_pen": 0,
            "dmg_reduction": 0,
            "lifesteal": 0,
            "crit_chance_reduction": 0
        },
        "set": null
    },
    {
        "ingame_id": "EPIC_RESIDUALLION_STONE_1",
        "id": "EPIC_RESIDUALLION_STONE_1",
        "name": "TEXT_EPIC_RESIDUALLION_STONE_1_TITLE",
        "description": "TEXT_EPIC_RESIDUALLION_STONE_1_DESC",
        "image": "ui_item_stone_1_legend_43",
        "grade": 1,
        "rarity": "epic",
        "sell_cost": 2000,
        "extract_cost": 500000,
        "stats": {
            "atk_power": 500,
            "hp": 0,
            "crit_chance": 0,
            "armor": 0,
            "resistance": 0,
            "crit_dmg": 0,
            "accuracy": 0,
            "evasion": 0,
            "armor_pen": 0,
            "resistance_pen": 0,
            "dmg_reduction": 0,
            "lifesteal": 0,
            "crit_chance_reduction": 0
        },
        "set": null
    },
    {
        "ingame_id": "EPIC_RESIDUALLION_STONE_2",
        "id": "EPIC_RESIDUALLION_STONE_2",
        "name": "TEXT_EPIC_RESIDUALLION_STONE_2_TITLE",
        "description": "TEXT_EPIC_RESIDUALLION_STONE_2_DESC",
        "image": "ui_item_stone_1_legend_44",
        "grade": 1,
        "rarity": "epic",
        "sell_cost": 2000,
        "extract_cost": 500000,
        "stats": {
            "atk_power": 0,
            "hp": 0,
            "crit_chance": 0,
            "armor": 0,
            "resistance": 500,
            "crit_dmg": 0,
            "accuracy": 0,
            "evasion": 0,
            "armor_pen": 0,
            "resistance_pen": 0,
            "dmg_reduction": 0,
            "lifesteal": 0,
            "crit_chance_reduction": 0
        },
        "set": null
    },
    {
        "ingame_id": "EPIC_RESIDUALLION_STONE_3",
        "id": "EPIC_RESIDUALLION_STONE_3",
        "name": "TEXT_EPIC_RESIDUALLION_STONE_3_TITLE",
        "description": "TEXT_EPIC_RESIDUALLION_STONE_3_DESC",
        "image": "ui_item_stone_1_legend_45",
        "grade": 1,
        "rarity": "epic",
        "sell_cost": 2000,
        "extract_cost": 500000,
        "stats": {
            "atk_power": 0,
            "hp": 20000,
            "crit_chance": 0,
            "armor": 0,
            "resistance": 0,
            "crit_dmg": 0,
            "accuracy": 0,
            "evasion": 0,
            "armor_pen": 0,
            "resistance_pen": 0,
            "dmg_reduction": 0,
            "lifesteal": 0,
            "crit_chance_reduction": 0
        },
        "set": null
    },
    {
        "ingame_id": "EPIC_RST_STONE_1",
        "id": "EPIC_RST_STONE_1",
        "name": "TEXT_EPIC_RST_STONE_1_TITLE",
        "description": "TEXT_EPIC_RST_STONE_1_DESC",
        "image": "ui_item_stone_1_def",
        "grade": 1,
        "rarity": "epic",
        "sell_cost": 2000,
        "extract_cost": 500000,
        "stats": {
            "atk_power": 0,
            "hp": 0,
            "crit_chance": 0,
            "armor": 0,
            "resistance": 500,
            "crit_dmg": 0,
            "accuracy": 0,
            "evasion": 0,
            "armor_pen": 0,
            "resistance_pen": 0,
            "dmg_reduction": 0,
            "lifesteal": 0,
            "crit_chance_reduction": 0
        },
        "set": null
    },
    {
        "ingame_id": "EPIC_RUDERAT_STONE_1",
        "id": "EPIC_RUDERAT_STONE_1",
        "name": "TEXT_EPIC_RUDERAT_STONE_1_TITLE",
        "description": "TEXT_EPIC_RUDERAT_STONE_1_DESC",
        "image": "ui_item_stone_1_legend_40",
        "grade": 1,
        "rarity": "epic",
        "sell_cost": 2000,
        "extract_cost": 500000,
        "stats": {
            "atk_power": 0,
            "hp": 0,
            "crit_chance": 0.03,
            "armor": 0,
            "resistance": 0,
            "crit_dmg": 0,
            "accuracy": 0,
            "evasion": 0,
            "armor_pen": 0,
            "resistance_pen": 0,
            "dmg_reduction": 0,
            "lifesteal": 0,
            "crit_chance_reduction": 0
        },
        "set": null
    },
    {
        "ingame_id": "EPIC_RUDERAT_STONE_2",
        "id": "EPIC_RUDERAT_STONE_2",
        "name": "TEXT_EPIC_RUDERAT_STONE_2_TITLE",
        "description": "TEXT_EPIC_RUDERAT_STONE_2_DESC",
        "image": "ui_item_stone_1_legend_41",
        "grade": 1,
        "rarity": "epic",
        "sell_cost": 2000,
        "extract_cost": 500000,
        "stats": {
            "atk_power": 0,
            "hp": 0,
            "crit_chance": 0,
            "armor": 0,
            "resistance": 0,
            "crit_dmg": 0,
            "accuracy": 0,
            "evasion": 0.05,
            "armor_pen": 0,
            "resistance_pen": 0,
            "dmg_reduction": 0,
            "lifesteal": 0,
            "crit_chance_reduction": 0
        },
        "set": null
    },
    {
        "ingame_id": "EPIC_RUDERAT_STONE_3",
        "id": "EPIC_RUDERAT_STONE_3",
        "name": "TEXT_EPIC_RUDERAT_STONE_3_TITLE",
        "description": "TEXT_EPIC_RUDERAT_STONE_3_DESC",
        "image": "ui_item_stone_1_legend_42",
        "grade": 1,
        "rarity": "epic",
        "sell_cost": 2000,
        "extract_cost": 500000,
        "stats": {
            "atk_power": 0,
            "hp": 20000,
            "crit_chance": 0,
            "armor": 0,
            "resistance": 0,
            "crit_dmg": 0,
            "accuracy": 0,
            "evasion": 0,
            "armor_pen": 0,
            "resistance_pen": 0,
            "dmg_reduction": 0,
            "lifesteal": 0,
            "crit_chance_reduction": 0
        },
        "set": null
    },
    {
        "ingame_id": "EPIC_SET_DEFFENCE_STONE_1",
        "id": "EPIC_SET_DEFFENCE_STONE_1",
        "name": "TEXT_EPIC_SET_DEFFENCE_STONE_1_TITLE",
        "description": "TEXT_EPIC_SET_DEFFENCE_STONE_1_DESC",
        "image": "ui_item_stone_1_set_17",
        "grade": 1,
        "rarity": "epic",
        "sell_cost": 2000,
        "extract_cost": 500000,
        "stats": {
            "atk_power": 0,
            "hp": 20000,
            "crit_chance": 0,
            "armor": 500,
            "resistance": 0,
            "crit_dmg": 0,
            "accuracy": 0,
            "evasion": 0,
            "armor_pen": 0,
            "resistance_pen": 0,
            "dmg_reduction": 0,
            "lifesteal": 0,
            "crit_chance_reduction": 0
        },
        "set": {
            "name": "TEXT_EPIC_SET_EP1_DEFENCE_1_NAME",
            "effect": "TEXT_EPIC_SET_EP1_DEFENCE_1_DESC",
            "pair": "EPIC_ANCIENREGIME_STONE_3"
        }
    },
    {
        "ingame_id": "EPIC_SET_DEFFENCE_STONE_2",
        "id": "EPIC_SET_DEFFENCE_STONE_2",
        "name": "TEXT_EPIC_SET_DEFFENCE_STONE_2_TITLE",
        "description": "TEXT_EPIC_SET_DEFFENCE_STONE_2_DESC",
        "image": "ui_item_stone_1_set_18",
        "grade": 1,
        "rarity": "epic",
        "sell_cost": 2000,
        "extract_cost": 500000,
        "stats": {
            "atk_power": 0,
            "hp": 20000,
            "crit_chance": 0,
            "armor": 0,
            "resistance": 500,
            "crit_dmg": 0,
            "accuracy": 0,
            "evasion": 0,
            "armor_pen": 0,
            "resistance_pen": 0,
            "dmg_reduction": 0,
            "lifesteal": 0,
            "crit_chance_reduction": 0
        },
        "set": {
            "name": "TEXT_EPIC_SET_EP1_DEFENCE_2_NAME",
            "effect": "TEXT_EPIC_SET_EP1_DEFENCE_2_DESC",
            "pair": "EPIC_ANCIENREGIME_STONE_2"
        }
    },
    {
        "ingame_id": "EPIC_SET_HEAL_STONE_1",
        "id": "EPIC_SET_HEAL_STONE_1",
        "name": "TEXT_EPIC_SET_HEAL_STONE_1_TITLE",
        "description": "TEXT_EPIC_SET_HEAL_STONE_1_DESC",
        "image": "ui_item_stone_1_set_23",
        "grade": 1,
        "rarity": "epic",
        "sell_cost": 2000,
        "extract_cost": 500000,
        "stats": {
            "atk_power": 500,
            "hp": 0,
            "crit_chance": 0,
            "armor": 0,
            "resistance": 0,
            "crit_dmg": 0,
            "accuracy": 0,
            "evasion": 0,
            "armor_pen": 0,
            "resistance_pen": 0,
            "dmg_reduction": 0,
            "lifesteal": 0,
            "crit_chance_reduction": 0
        },
        "set": {
            "name": "TEXT_EPIC_SET_EP1_HEAL_1_NAME",
            "effect": "TEXT_EPIC_SET_EP1_HEAL_1_DESC",
            "pair": "EPIC_AVENIR_STONE_2"
        }
    },
    {
        "ingame_id": "EPIC_SET_HEAL_STONE_2",
        "id": "EPIC_SET_HEAL_STONE_2",
        "name": "TEXT_EPIC_SET_HEAL_STONE_2_TITLE",
        "description": "TEXT_EPIC_SET_HEAL_STONE_2_DESC",
        "image": "ui_item_stone_1_set_24",
        "grade": 1,
        "rarity": "epic",
        "sell_cost": 2000,
        "extract_cost": 500000,
        "stats": {
            "atk_power": 0,
            "hp": 20000,
            "crit_chance": 0,
            "armor": 0,
            "resistance": 0,
            "crit_dmg": 0,
            "accuracy": 0,
            "evasion": 0.05,
            "armor_pen": 0,
            "resistance_pen": 0,
            "dmg_reduction": 0,
            "lifesteal": 0,
            "crit_chance_reduction": 0
        },
        "set": {
            "name": "TEXT_EPIC_SET_EP1_HEAL_2_NAME",
            "effect": "TEXT_EPIC_SET_EP1_HEAL_2_DESC",
            "pair": "EPIC_AVENIR_STONE_1"
        }
    },
    {
        "ingame_id": "EPIC_SET_MAGIC_STONE_1",
        "id": "EPIC_SET_MAGIC_STONE_1",
        "name": "TEXT_EPIC_SET_MAGIC_STONE_1_TITLE",
        "description": "TEXT_EPIC_SET_MAGIC_STONE_1_DESC",
        "image": "ui_item_stone_1_set_21",
        "grade": 1,
        "rarity": "epic",
        "sell_cost": 2000,
        "extract_cost": 500000,
        "stats": {
            "atk_power": 500,
            "hp": 0,
            "crit_chance": 0,
            "armor": 0,
            "resistance": 0,
            "crit_dmg": 0,
            "accuracy": 0.05,
            "evasion": 0,
            "armor_pen": 0,
            "resistance_pen": 0,
            "dmg_reduction": 0,
            "lifesteal": 0,
            "crit_chance_reduction": 0
        },
        "set": {
            "name": "TEXT_EPIC_SET_EP1_MAGIC_1_NAME",
            "effect": "TEXT_EPIC_SET_EP1_MAGIC_1_DESC",
            "pair": "EPIC_3G_STONE_1"
        }
    },
    {
        "ingame_id": "EPIC_SET_MAGIC_STONE_2",
        "id": "EPIC_SET_MAGIC_STONE_2",
        "name": "TEXT_EPIC_SET_MAGIC_STONE_2_TITLE",
        "description": "TEXT_EPIC_SET_MAGIC_STONE_2_DESC",
        "image": "ui_item_stone_1_set_22",
        "grade": 1,
        "rarity": "epic",
        "sell_cost": 2000,
        "extract_cost": 500000,
        "stats": {
            "atk_power": 0,
            "hp": 0,
            "crit_chance": 0.03,
            "armor": 0,
            "resistance": 0,
            "crit_dmg": 0,
            "accuracy": 0,
            "evasion": 0,
            "armor_pen": 0,
            "resistance_pen": 500,
            "dmg_reduction": 0,
            "lifesteal": 0,
            "crit_chance_reduction": 0
        },
        "set": {
            "name": "TEXT_EPIC_SET_EP1_MAGIC_2_NAME",
            "effect": "TEXT_EPIC_SET_EP1_MAGIC_2_DESC",
            "pair": "EPIC_AZATHOTH_STONE_3"
        }
    },
    {
        "ingame_id": "EPIC_SET_PHYSIC_STONE_1",
        "id": "EPIC_SET_PHYSIC_STONE_1",
        "name": "TEXT_EPIC_SET_PHYSIC_STONE_1_TITLE",
        "description": "TEXT_EPIC_SET_PHYSIC_STONE_1_DESC",
        "image": "ui_item_stone_1_set_19",
        "grade": 1,
        "rarity": "epic",
        "sell_cost": 2000,
        "extract_cost": 500000,
        "stats": {
            "atk_power": 500,
            "hp": 0,
            "crit_chance": 0,
            "armor": 0,
            "resistance": 0,
            "crit_dmg": 0,
            "accuracy": 0.05,
            "evasion": 0,
            "armor_pen": 0,
            "resistance_pen": 0,
            "dmg_reduction": 0,
            "lifesteal": 0,
            "crit_chance_reduction": 0
        },
        "set": {
            "name": "TEXT_EPIC_SET_EP1_PHYSIC_1_NAME",
            "effect": "TEXT_EPIC_SET_EP1_PHYSIC_1_DESC",
            "pair": "EPIC_REBOUILLABAISSE_STONE_3"
        }
    },
    {
        "ingame_id": "EPIC_SET_PHYSIC_STONE_2",
        "id": "EPIC_SET_PHYSIC_STONE_2",
        "name": "TEXT_EPIC_SET_PHYSIC_STONE_2_TITLE",
        "description": "TEXT_EPIC_SET_PHYSIC_STONE_2_DESC",
        "image": "ui_item_stone_1_set_20",
        "grade": 1,
        "rarity": "epic",
        "sell_cost": 2000,
        "extract_cost": 500000,
        "stats": {
            "atk_power": 0,
            "hp": 0,
            "crit_chance": 0.03,
            "armor": 0,
            "resistance": 0,
            "crit_dmg": 0,
            "accuracy": 0,
            "evasion": 0,
            "armor_pen": 500,
            "resistance_pen": 0,
            "dmg_reduction": 0,
            "lifesteal": 0,
            "crit_chance_reduction": 0
        },
        "set": {
            "name": "TEXT_EPIC_SET_EP1_PHYSIC_2_NAME",
            "effect": "TEXT_EPIC_SET_EP1_PHYSIC_2_DESC",
            "pair": "EPIC_AZATHOTH_STONE_2"
        }
    },
    {
        "ingame_id": "RARE_3G_STONE_1",
        "id": "RARE_3G_STONE_1",
        "name": "TEXT_RARE_3G_STONE_1_TITLE",
        "description": "TEXT_RARE_3G_STONE_1_DESC",
        "image": "ui_item_stone_1_legend_34",
        "grade": 1,
        "rarity": "rare",
        "sell_cost": 1000,
        "extract_cost": 300000,
        "stats": {
            "atk_power": 0,
            "hp": 0,
            "crit_chance": 0,
            "armor": 0,
            "resistance": 0,
            "crit_dmg": 0,
            "accuracy": 0,
            "evasion": 0,
            "armor_pen": 0,
            "resistance_pen": 0,
            "dmg_reduction": 0.02,
            "lifesteal": 0,
            "crit_chance_reduction": 0
        },
        "set": null
    },
    {
        "ingame_id": "RARE_3G_STONE_2",
        "id": "RARE_3G_STONE_2",
        "name": "TEXT_RARE_3G_STONE_2_TITLE",
        "description": "TEXT_RARE_3G_STONE_2_DESC",
        "image": "ui_item_stone_1_legend_35",
        "grade": 1,
        "rarity": "rare",
        "sell_cost": 1000,
        "extract_cost": 300000,
        "stats": {
            "atk_power": 300,
            "hp": 0,
            "crit_chance": 0,
            "armor": 0,
            "resistance": 0,
            "crit_dmg": 0,
            "accuracy": 0,
            "evasion": 0,
            "armor_pen": 0,
            "resistance_pen": 0,
            "dmg_reduction": 0,
            "lifesteal": 0,
            "crit_chance_reduction": 0
        },
        "set": null
    },
    {
        "ingame_id": "RARE_ACCURACY_RATE_STONE_1",
        "id": "RARE_ACCURACY_RATE_STONE_1",
        "name": "TEXT_RARE_ACCURACY_RATE_STONE_1_TITLE",
        "description": "TEXT_RARE_ACCURACY_RATE_STONE_1_DESC",
        "image": "ui_item_stone_1_func",
        "grade": 1,
        "rarity": "rare",
        "sell_cost": 1000,
        "extract_cost": 300000,
        "stats": {
            "atk_power": 0,
            "hp": 0,
            "crit_chance": 0,
            "armor": 0,
            "resistance": 0,
            "crit_dmg": 0,
            "accuracy": 0.03,
            "evasion": 0,
            "armor_pen": 0,
            "resistance_pen": 0,
            "dmg_reduction": 0,
            "lifesteal": 0,
            "crit_chance_reduction": 0
        },
        "set": null
    },
    {
        "ingame_id": "RARE_ATK_POWER_STONE_1",
        "id": "RARE_ATK_POWER_STONE_1",
        "name": "TEXT_RARE_ATK_POWER_STONE_1_TITLE",
        "description": "TEXT_RARE_ATK_POWER_STONE_1_DESC",
        "image": "ui_item_stone_1_atk",
        "grade": 1,
        "rarity": "rare",
        "sell_cost": 1000,
        "extract_cost": 300000,
        "stats": {
            "atk_power": 300,
            "hp": 0,
            "crit_chance": 0,
            "armor": 0,
            "resistance": 0,
            "crit_dmg": 0,
            "accuracy": 0,
            "evasion": 0,
            "armor_pen": 0,
            "resistance_pen": 0,
            "dmg_reduction": 0,
            "lifesteal": 0,
            "crit_chance_reduction": 0
        },
        "set": null
    },
    {
        "ingame_id": "RARE_BOUILLABAISSE_STONE_1",
        "id": "RARE_BOUILLABAISSE_STONE_1",
        "name": "TEXT_RARE_BOUILLABAISSE_STONE_1_TITLE",
        "description": "TEXT_RARE_BOUILLABAISSE_STONE_1_DESC",
        "image": "ui_item_stone_1_legend_21",
        "grade": 1,
        "rarity": "rare",
        "sell_cost": 1000,
        "extract_cost": 300000,
        "stats": {
            "atk_power": 300,
            "hp": 0,
            "crit_chance": 0,
            "armor": 0,
            "resistance": 0,
            "crit_dmg": 0,
            "accuracy": 0,
            "evasion": 0,
            "armor_pen": 0,
            "resistance_pen": 0,
            "dmg_reduction": 0,
            "lifesteal": 0,
            "crit_chance_reduction": 0
        },
        "set": null
    },
    {
        "ingame_id": "RARE_CRIT_DODGE_RATE_STONE_1",
        "id": "RARE_CRIT_DODGE_RATE_STONE_1",
        "name": "TEXT_RARE_CRIT_DODGE_RATE_STONE_1_TITLE",
        "description": "TEXT_RARE_CRIT_DODGE_RATE_STONE_1_DESC",
        "image": "ui_item_stone_1_def",
        "grade": 1,
        "rarity": "rare",
        "sell_cost": 1000,
        "extract_cost": 300000,
        "stats": {
            "atk_power": 0,
            "hp": 0,
            "crit_chance": 0,
            "armor": 0,
            "resistance": 0,
            "crit_dmg": 0,
            "accuracy": 0,
            "evasion": 0,
            "armor_pen": 0,
            "resistance_pen": 0,
            "dmg_reduction": 0,
            "lifesteal": 0,
            "crit_chance_reduction": 0.02
        },
        "set": null
    },
    {
        "ingame_id": "RARE_CRIT_RATE_STONE_1",
        "id": "RARE_CRIT_RATE_STONE_1",
        "name": "TEXT_RARE_CRIT_RATE_STONE_1_TITLE",
        "description": "TEXT_RARE_CRIT_RATE_STONE_1_DESC",
        "image": "ui_item_stone_1_func",
        "grade": 1,
        "rarity": "rare",
        "sell_cost": 1000,
        "extract_cost": 300000,
        "stats": {
            "atk_power": 0,
            "hp": 0,
            "crit_chance": 0.02,
            "armor": 0,
            "resistance": 0,
            "crit_dmg": 0,
            "accuracy": 0,
            "evasion": 0,
            "armor_pen": 0,
            "resistance_pen": 0,
            "dmg_reduction": 0,
            "lifesteal": 0,
            "crit_chance_reduction": 0
        },
        "set": null
    },
    {
        "ingame_id": "RARE_DEF_STONE_1",
        "id": "RARE_DEF_STONE_1",
        "name": "TEXT_RARE_DEF_STONE_1_TITLE",
        "description": "TEXT_RARE_DEF_STONE_1_DESC",
        "image": "ui_item_stone_1_def",
        "grade": 1,
        "rarity": "rare",
        "sell_cost": 1000,
        "extract_cost": 300000,
        "stats": {
            "atk_power": 0,
            "hp": 0,
            "crit_chance": 0,
            "armor": 300,
            "resistance": 0,
            "crit_dmg": 0,
            "accuracy": 0,
            "evasion": 0,
            "armor_pen": 0,
            "resistance_pen": 0,
            "dmg_reduction": 0,
            "lifesteal": 0,
            "crit_chance_reduction": 0
        },
        "set": null
    },
    {
        "ingame_id": "RARE_DODGE_RATE_STONE_1",
        "id": "RARE_DODGE_RATE_STONE_1",
        "name": "TEXT_RARE_DODGE_RATE_STONE_1_TITLE",
        "description": "TEXT_RARE_DODGE_RATE_STONE_1_DESC",
        "image": "ui_item_stone_1_func",
        "grade": 1,
        "rarity": "rare",
        "sell_cost": 1000,
        "extract_cost": 300000,
        "stats": {
            "atk_power": 0,
            "hp": 0,
            "crit_chance": 0,
            "armor": 0,
            "resistance": 0,
            "crit_dmg": 0,
            "accuracy": 0,
            "evasion": 0.03,
            "armor_pen": 0,
            "resistance_pen": 0,
            "dmg_reduction": 0,
            "lifesteal": 0,
            "crit_chance_reduction": 0
        },
        "set": null
    },
    {
        "ingame_id": "RARE_DOMPERIGNON_STONE_1",
        "id": "RARE_DOMPERIGNON_STONE_1",
        "name": "TEXT_RARE_DOMPERIGNON_STONE_1_TITLE",
        "description": "TEXT_RARE_DOMPERIGNON_STONE_1_DESC",
        "image": "ui_item_stone_1_legend_18",
        "grade": 1,
        "rarity": "rare",
        "sell_cost": 1000,
        "extract_cost": 300000,
        "stats": {
            "atk_power": 0,
            "hp": 0,
            "crit_chance": 0,
            "armor": 0,
            "resistance": 300,
            "crit_dmg": 0,
            "accuracy": 0,
            "evasion": 0,
            "armor_pen": 0,
            "resistance_pen": 0,
            "dmg_reduction": 0,
            "lifesteal": 0,
            "crit_chance_reduction": 0
        },
        "set": null
    },
    {
        "ingame_id": "RARE_GG_STONE_1",
        "id": "RARE_GG_STONE_1",
        "name": "TEXT_RARE_GG_STONE_1_TITLE",
        "description": "TEXT_RARE_GG_STONE_1_DESC",
        "image": "ui_item_stone_1_legend_28",
        "grade": 1,
        "rarity": "rare",
        "sell_cost": 1000,
        "extract_cost": 300000,
        "stats": {
            "atk_power": 0,
            "hp": 0,
            "crit_chance": 0,
            "armor": 0,
            "resistance": 0,
            "crit_dmg": 0,
            "accuracy": 0.03,
            "evasion": 0,
            "armor_pen": 0,
            "resistance_pen": 0,
            "dmg_reduction": 0,
            "lifesteal": 0,
            "crit_chance_reduction": 0
        },
        "set": null
    },
    {
        "ingame_id": "RARE_GG_STONE_2",
        "id": "RARE_GG_STONE_2",
        "name": "TEXT_RARE_GG_STONE_2_TITLE",
        "description": "TEXT_RARE_GG_STONE_2_DESC",
        "image": "ui_item_stone_1_legend_29",
        "grade": 1,
        "rarity": "rare",
        "sell_cost": 1000,
        "extract_cost": 300000,
        "stats": {
            "atk_power": 0,
            "hp": 0,
            "crit_chance": 0,
            "armor": 0,
            "resistance": 0,
            "crit_dmg": 0,
            "accuracy": 0,
            "evasion": 0.03,
            "armor_pen": 0,
            "resistance_pen": 0,
            "dmg_reduction": 0,
            "lifesteal": 0,
            "crit_chance_reduction": 0
        },
        "set": null
    },
    {
        "ingame_id": "RARE_LEESIN_STONE_1",
        "id": "RARE_LEESIN_STONE_1",
        "name": "TEXT_RARE_LEESIN_STONE_1_TITLE",
        "description": "TEXT_RARE_LEESIN_STONE_1_DESC",
        "image": "ui_item_stone_1_legend_31",
        "grade": 1,
        "rarity": "rare",
        "sell_cost": 1000,
        "extract_cost": 300000,
        "stats": {
            "atk_power": 0,
            "hp": 0,
            "crit_chance": 0,
            "armor": 0,
            "resistance": 0,
            "crit_dmg": 0,
            "accuracy": 0,
            "evasion": 0,
            "armor_pen": 0,
            "resistance_pen": 0,
            "dmg_reduction": 0,
            "lifesteal": 0,
            "crit_chance_reduction": 0.02
        },
        "set": null
    },
    {
        "ingame_id": "RARE_LEESIN_STONE_2",
        "id": "RARE_LEESIN_STONE_2",
        "name": "TEXT_RARE_LEESIN_STONE_2_TITLE",
        "description": "TEXT_RARE_LEESIN_STONE_2_DESC",
        "image": "ui_item_stone_1_legend_32",
        "grade": 1,
        "rarity": "rare",
        "sell_cost": 1000,
        "extract_cost": 300000,
        "stats": {
            "atk_power": 0,
            "hp": 0,
            "crit_chance": 0.02,
            "armor": 0,
            "resistance": 0,
            "crit_dmg": 0,
            "accuracy": 0,
            "evasion": 0,
            "armor_pen": 0,
            "resistance_pen": 0,
            "dmg_reduction": 0,
            "lifesteal": 0,
            "crit_chance_reduction": 0
        },
        "set": null
    },
    {
        "ingame_id": "RARE_MATAHARI_STONE_1",
        "id": "RARE_MATAHARI_STONE_1",
        "name": "TEXT_RARE_MATAHARI_STONE_1_TITLE",
        "description": "TEXT_RARE_MATAHARI_STONE_1_DESC",
        "image": "ui_item_stone_1_legend_15",
        "grade": 1,
        "rarity": "rare",
        "sell_cost": 1000,
        "extract_cost": 300000,
        "stats": {
            "atk_power": 0,
            "hp": 0,
            "crit_chance": 0,
            "armor": 300,
            "resistance": 0,
            "crit_dmg": 0,
            "accuracy": 0,
            "evasion": 0,
            "armor_pen": 0,
            "resistance_pen": 0,
            "dmg_reduction": 0,
            "lifesteal": 0,
            "crit_chance_reduction": 0
        },
        "set": null
    },
    {
        "ingame_id": "RARE_MAX_HP_STONE_1",
        "id": "RARE_MAX_HP_STONE_1",
        "name": "TEXT_RARE_MAX_HP_STONE_1_TITLE",
        "description": "TEXT_RARE_MAX_HP_STONE_1_DESC",
        "image": "ui_item_stone_1_def",
        "grade": 1,
        "rarity": "rare",
        "sell_cost": 1000,
        "extract_cost": 300000,
        "stats": {
            "atk_power": 0,
            "hp": 12000,
            "crit_chance": 0,
            "armor": 0,
            "resistance": 0,
            "crit_dmg": 0,
            "accuracy": 0,
            "evasion": 0,
            "armor_pen": 0,
            "resistance_pen": 0,
            "dmg_reduction": 0,
            "lifesteal": 0,
            "crit_chance_reduction": 0
        },
        "set": null
    },
    {
        "ingame_id": "RARE_PENETRATE_DEF_STONE_1",
        "id": "RARE_PENETRATE_DEF_STONE_1",
        "name": "TEXT_RARE_PENETRATE_DEF_STONE_1_TITLE",
        "description": "TEXT_RARE_PENETRATE_DEF_STONE_1_DESC",
        "image": "ui_item_stone_1_atk",
        "grade": 1,
        "rarity": "rare",
        "sell_cost": 1000,
        "extract_cost": 300000,
        "stats": {
            "atk_power": 0,
            "hp": 0,
            "crit_chance": 0,
            "armor": 0,
            "resistance": 0,
            "crit_dmg": 0,
            "accuracy": 0,
            "evasion": 0,
            "armor_pen": 300,
            "resistance_pen": 0,
            "dmg_reduction": 0,
            "lifesteal": 0,
            "crit_chance_reduction": 0
        },
        "set": null
    },
    {
        "ingame_id": "RARE_PENETRATE_RST_STONE_1",
        "id": "RARE_PENETRATE_RST_STONE_1",
        "name": "TEXT_RARE_PENETRATE_RST_STONE_1_TITLE",
        "description": "TEXT_RARE_PENETRATE_RST_STONE_1_DESC",
        "image": "ui_item_stone_1_atk",
        "grade": 1,
        "rarity": "rare",
        "sell_cost": 1000,
        "extract_cost": 300000,
        "stats": {
            "atk_power": 0,
            "hp": 0,
            "crit_chance": 0,
            "armor": 0,
            "resistance": 0,
            "crit_dmg": 0,
            "accuracy": 0,
            "evasion": 0,
            "armor_pen": 0,
            "resistance_pen": 300,
            "dmg_reduction": 0,
            "lifesteal": 0,
            "crit_chance_reduction": 0
        },
        "set": null
    },
    {
        "ingame_id": "RARE_RECEIVE_DMG_RATE_STONE_1",
        "id": "RARE_RECEIVE_DMG_RATE_STONE_1",
        "name": "TEXT_RARE_RECEIVE_DMG_RATE_STONE_1_TITLE",
        "description": "TEXT_RARE_RECEIVE_DMG_RATE_STONE_1_DESC",
        "image": "ui_item_stone_1_def",
        "grade": 1,
        "rarity": "rare",
        "sell_cost": 1000,
        "extract_cost": 300000,
        "stats": {
            "atk_power": 0,
            "hp": 0,
            "crit_chance": 0,
            "armor": 0,
            "resistance": 0,
            "crit_dmg": 0,
            "accuracy": 0,
            "evasion": 0,
            "armor_pen": 0,
            "resistance_pen": 0,
            "dmg_reduction": 0.02,
            "lifesteal": 0,
            "crit_chance_reduction": 0
        },
        "set": null
    },
    {
        "ingame_id": "RARE_RST_STONE_1",
        "id": "RARE_RST_STONE_1",
        "name": "TEXT_RARE_RST_STONE_1_TITLE",
        "description": "TEXT_RARE_RST_STONE_1_DESC",
        "image": "ui_item_stone_1_def",
        "grade": 1,
        "rarity": "rare",
        "sell_cost": 1000,
        "extract_cost": 300000,
        "stats": {
            "atk_power": 0,
            "hp": 0,
            "crit_chance": 0,
            "armor": 0,
            "resistance": 300,
            "crit_dmg": 0,
            "accuracy": 0,
            "evasion": 0,
            "armor_pen": 0,
            "resistance_pen": 0,
            "dmg_reduction": 0,
            "lifesteal": 0,
            "crit_chance_reduction": 0
        },
        "set": null
    },
    {
        "ingame_id": "RARE_SET_DEFFENCE_STONE_1",
        "id": "RARE_SET_DEFFENCE_STONE_1",
        "name": "TEXT_RARE_SET_DEFFENCE_STONE_1_TITLE",
        "description": "TEXT_RARE_SET_DEFFENCE_STONE_1_DESC",
        "image": "ui_item_stone_1_set_09",
        "grade": 1,
        "rarity": "rare",
        "sell_cost": 1000,
        "extract_cost": 500000,
        "stats": {
            "atk_power": 0,
            "hp": 12000,
            "crit_chance": 0,
            "armor": 0,
            "resistance": 0,
            "crit_dmg": 0,
            "accuracy": 0,
            "evasion": 0,
            "armor_pen": 0,
            "resistance_pen": 0,
            "dmg_reduction": 0,
            "lifesteal": 0,
            "crit_chance_reduction": 0
        },
        "set": {
            "name": "TEXT_RARE_SET_EP1_DEFENCE_1_NAME",
            "effect": "TEXT_RARE_SET_EP1_DEFENCE_1_DESC",
            "pair": "RARE_MATAHARI_STONE_1"
        }
    },
    {
        "ingame_id": "RARE_SET_DEFFENCE_STONE_2",
        "id": "RARE_SET_DEFFENCE_STONE_2",
        "name": "TEXT_RARE_SET_DEFFENCE_STONE_2_TITLE",
        "description": "TEXT_RARE_SET_DEFFENCE_STONE_2_DESC",
        "image": "ui_item_stone_1_set_10",
        "grade": 1,
        "rarity": "rare",
        "sell_cost": 1000,
        "extract_cost": 500000,
        "stats": {
            "atk_power": 0,
            "hp": 0,
            "crit_chance": 0,
            "armor": 0,
            "resistance": 0,
            "crit_dmg": 0,
            "accuracy": 0,
            "evasion": 0,
            "armor_pen": 0,
            "resistance_pen": 0,
            "dmg_reduction": 0.02,
            "lifesteal": 0,
            "crit_chance_reduction": 0
        },
        "set": {
            "name": "TEXT_RARE_SET_EP1_DEFENCE_2_NAME",
            "effect": "TEXT_RARE_SET_EP1_DEFENCE_2_DESC",
            "pair": "RARE_DOMPERIGNON_STONE_1"
        }
    },
    {
        "ingame_id": "RARE_SET_HEAL_STONE_1",
        "id": "RARE_SET_HEAL_STONE_1",
        "name": "TEXT_RARE_SET_HEAL_STONE_1_TITLE",
        "description": "TEXT_RARE_SET_HEAL_STONE_1_DESC",
        "image": "ui_item_stone_1_set_15",
        "grade": 1,
        "rarity": "rare",
        "sell_cost": 1000,
        "extract_cost": 500000,
        "stats": {
            "atk_power": 300,
            "hp": 0,
            "crit_chance": 0,
            "armor": 0,
            "resistance": 0,
            "crit_dmg": 0,
            "accuracy": 0,
            "evasion": 0,
            "armor_pen": 0,
            "resistance_pen": 0,
            "dmg_reduction": 0,
            "lifesteal": 0,
            "crit_chance_reduction": 0
        },
        "set": {
            "name": "TEXT_RARE_SET_EP1_HEAL_1_NAME",
            "effect": "TEXT_RARE_SET_EP1_HEAL_1_DESC",
            "pair": "RARE_3G_STONE_2"
        }
    },
    {
        "ingame_id": "RARE_SET_HEAL_STONE_2",
        "id": "RARE_SET_HEAL_STONE_2",
        "name": "TEXT_RARE_SET_HEAL_STONE_2_TITLE",
        "description": "TEXT_RARE_SET_HEAL_STONE_2_DESC",
        "image": "ui_item_stone_1_set_16",
        "grade": 1,
        "rarity": "rare",
        "sell_cost": 1000,
        "extract_cost": 500000,
        "stats": {
            "atk_power": 0,
            "hp": 12000,
            "crit_chance": 0,
            "armor": 0,
            "resistance": 0,
            "crit_dmg": 0,
            "accuracy": 0,
            "evasion": 0,
            "armor_pen": 0,
            "resistance_pen": 0,
            "dmg_reduction": 0,
            "lifesteal": 0,
            "crit_chance_reduction": 0
        },
        "set": {
            "name": "TEXT_RARE_SET_EP1_HEAL_2_NAME",
            "effect": "TEXT_RARE_SET_EP1_HEAL_2_DESC",
            "pair": "RARE_SHADOWDEVILFINAL_STONE_3"
        }
    },
    {
        "ingame_id": "RARE_SET_MAGIC_STONE_1",
        "id": "RARE_SET_MAGIC_STONE_1",
        "name": "TEXT_RARE_SET_MAGIC_STONE_1_TITLE",
        "description": "TEXT_RARE_SET_MAGIC_STONE_1_DESC",
        "image": "ui_item_stone_1_set_13",
        "grade": 1,
        "rarity": "rare",
        "sell_cost": 1000,
        "extract_cost": 500000,
        "stats": {
            "atk_power": 300,
            "hp": 0,
            "crit_chance": 0,
            "armor": 0,
            "resistance": 0,
            "crit_dmg": 0,
            "accuracy": 0,
            "evasion": 0,
            "armor_pen": 0,
            "resistance_pen": 0,
            "dmg_reduction": 0,
            "lifesteal": 0,
            "crit_chance_reduction": 0
        },
        "set": {
            "name": "TEXT_RARE_SET_EP1_MAGIC_1_NAME",
            "effect": "TEXT_RARE_SET_EP1_MAGIC_1_DESC",
            "pair": "RARE_GG_STONE_1"
        }
    },
    {
        "ingame_id": "RARE_SET_MAGIC_STONE_2",
        "id": "RARE_SET_MAGIC_STONE_2",
        "name": "TEXT_RARE_SET_MAGIC_STONE_2_TITLE",
        "description": "TEXT_RARE_SET_MAGIC_STONE_2_DESC",
        "image": "ui_item_stone_1_set_14",
        "grade": 1,
        "rarity": "rare",
        "sell_cost": 1000,
        "extract_cost": 500000,
        "stats": {
            "atk_power": 0,
            "hp": 0,
            "crit_chance": 0,
            "armor": 0,
            "resistance": 0,
            "crit_dmg": 0,
            "accuracy": 0,
            "evasion": 0,
            "armor_pen": 0,
            "resistance_pen": 300,
            "dmg_reduction": 0,
            "lifesteal": 0,
            "crit_chance_reduction": 0
        },
        "set": {
            "name": "TEXT_RARE_SET_EP1_MAGIC_2_NAME",
            "effect": "TEXT_RARE_SET_EP1_MAGIC_2_DESC",
            "pair": "RARE_LEESIN_STONE_1"
        }
    },
    {
        "ingame_id": "RARE_SET_PHYSIC_STONE_1",
        "id": "RARE_SET_PHYSIC_STONE_1",
        "name": "TEXT_RARE_SET_PHYSIC_STONE_1_TITLE",
        "description": "TEXT_RARE_SET_PHYSIC_STONE_1_DESC",
        "image": "ui_item_stone_1_set_11",
        "grade": 1,
        "rarity": "rare",
        "sell_cost": 1000,
        "extract_cost": 500000,
        "stats": {
            "atk_power": 300,
            "hp": 0,
            "crit_chance": 0,
            "armor": 0,
            "resistance": 0,
            "crit_dmg": 0,
            "accuracy": 0,
            "evasion": 0,
            "armor_pen": 0,
            "resistance_pen": 0,
            "dmg_reduction": 0,
            "lifesteal": 0,
            "crit_chance_reduction": 0
        },
        "set": {
            "name": "TEXT_RARE_SET_EP1_PHYSIC_1_NAME",
            "effect": "TEXT_RARE_SET_EP1_PHYSIC_1_DESC",
            "pair": "RARE_SHADOWDEVILFINAL_STONE_1"
        }
    },
    {
        "ingame_id": "RARE_SET_PHYSIC_STONE_2",
        "id": "RARE_SET_PHYSIC_STONE_2",
        "name": "TEXT_RARE_SET_PHYSIC_STONE_2_TITLE",
        "description": "TEXT_RARE_SET_PHYSIC_STONE_2_DESC",
        "image": "ui_item_stone_1_set_12",
        "grade": 1,
        "rarity": "rare",
        "sell_cost": 1000,
        "extract_cost": 500000,
        "stats": {
            "atk_power": 0,
            "hp": 0,
            "crit_chance": 0,
            "armor": 0,
            "resistance": 0,
            "crit_dmg": 0,
            "accuracy": 0,
            "evasion": 0,
            "armor_pen": 300,
            "resistance_pen": 0,
            "dmg_reduction": 0,
            "lifesteal": 0,
            "crit_chance_reduction": 0
        },
        "set": {
            "name": "TEXT_RARE_SET_EP1_PHYSIC_2_NAME",
            "effect": "TEXT_RARE_SET_EP1_PHYSIC_2_DESC",
            "pair": "RARE_BOUILLABAISSE_STONE_1"
        }
    },
    {
        "ingame_id": "RARE_SHADOWDEVILFINAL_STONE_1",
        "id": "RARE_SHADOWDEVILFINAL_STONE_1",
        "name": "TEXT_RARE_SHADOWDEVILFINAL_STONE_1_TITLE",
        "description": "TEXT_RARE_SHADOWDEVILFINAL_STONE_1_DESC",
        "image": "ui_item_stone_1_legend_25",
        "grade": 1,
        "rarity": "rare",
        "sell_cost": 1000,
        "extract_cost": 300000,
        "stats": {
            "atk_power": 0,
            "hp": 0,
            "crit_chance": 0,
            "armor": 0,
            "resistance": 0,
            "crit_dmg": 0,
            "accuracy": 0.03,
            "evasion": 0,
            "armor_pen": 0,
            "resistance_pen": 0,
            "dmg_reduction": 0,
            "lifesteal": 0,
            "crit_chance_reduction": 0
        },
        "set": null
    },
    {
        "ingame_id": "RARE_SHADOWDEVILFINAL_STONE_2",
        "id": "RARE_SHADOWDEVILFINAL_STONE_2",
        "name": "TEXT_RARE_SHADOWDEVILFINAL_STONE_2_TITLE",
        "description": "TEXT_RARE_SHADOWDEVILFINAL_STONE_2_DESC",
        "image": "ui_item_stone_1_legend_26",
        "grade": 1,
        "rarity": "rare",
        "sell_cost": 1000,
        "extract_cost": 300000,
        "stats": {
            "atk_power": 0,
            "hp": 0,
            "crit_chance": 0,
            "armor": 0,
            "resistance": 0,
            "crit_dmg": 0,
            "accuracy": 0,
            "evasion": 0.03,
            "armor_pen": 0,
            "resistance_pen": 0,
            "dmg_reduction": 0,
            "lifesteal": 0,
            "crit_chance_reduction": 0
        },
        "set": null
    },
    {
        "ingame_id": "RARE_SHADOWDEVILFINAL_STONE_3",
        "id": "RARE_SHADOWDEVILFINAL_STONE_3",
        "name": "TEXT_RARE_SHADOWDEVILFINAL_STONE_3_TITLE",
        "description": "TEXT_RARE_SHADOWDEVILFINAL_STONE_3_DESC",
        "image": "ui_item_stone_1_legend_27",
        "grade": 1,
        "rarity": "rare",
        "sell_cost": 1000,
        "extract_cost": 300000,
        "stats": {
            "atk_power": 0,
            "hp": 12000,
            "crit_chance": 0,
            "armor": 0,
            "resistance": 0,
            "crit_dmg": 0,
            "accuracy": 0,
            "evasion": 0,
            "armor_pen": 0,
            "resistance_pen": 0,
            "dmg_reduction": 0,
            "lifesteal": 0,
            "crit_chance_reduction": 0
        },
        "set": null
    }
]